Workbook

Sheet Как пользоваться
A1: План уроков по грамматике Spotlight
A3: «Темы × классы»: строка = подтема (один короткий урок: видео → правило → мини-тест). Подтемы сгруппированы по темам: Past Simple делится на правильные/неправильные глаголы, утверждение, отрицание, вопросы, орфографию, каждое значение; сравнения времён — отдельными подтемами.
A4: В клетке класса — где в учебнике (М9 (9b) = Module 9, урок 9b) и статус: «новое» — подтема в Spotlight впервые; «расш.» — была, здесь добавлено; «повт.» — дана снова. Наведите на клетку — во всплывающей подсказке что именно дано (лица, слова-сигналы, список глаголов).
A5: Цвет клетки: оттенок = группа вебинара (оранжевый 7–9 лет, голубой 10+), насыщенность = статус (ярче — новое, бледнее — повторение).
A6: Группы вебинаров: 7–9 лет = Spotlight 2–4 (у Spotlight 2 нет грамматического справочника, поэтому 2 класса нет; 4 класс — в группе 7–9, его темы идут в вебинарах 7–9). 10+ = Spotlight 5–11.
A7: Цвет подтемы: ЗЕЛЁНЫЙ — есть видео; ЖЁЛТЫЙ — вебинар в расписании (материалы есть, после вебинара появится видео; рядом дата, «проведён, ждём видео» — если дата прошла); ОРАНЖЕВЫЙ — видео нет, но есть материалы в папке; КРАСНЫЙ — ничего нет. Если подтема нужна обеим группам, цвет — по худшей из двух; по каждой группе — в колонках «Видео 7–9» / «Видео 10+» (видео / вебинар / материалы / нет), рядом названия видео, дата вебинара или папки с материалами. «—» — подтема этой группе не нужна.
A8: «Уроки»: один урок = подтема × группа. Если подтема повторяется в нескольких классах одной группы, это один и тот же урок (Мл-… для 7–9 лет, Ст-… для 10+): в колонке «Где используется» — все классы и модули. Видео подтягивается из «Темы × классы»; «Готовность» отмечается здесь.
A9: «Папки уроков»: Spotlight / класс / модуль / тема (папка) / подтема — какой урок (№) куда положить. Видео и готовность подтягиваются из «Уроков».
A10: «Пересечения»: одна и та же вещь в двух-трёх темах — где предлагаю держать урок, где поставить ссылку.
A11: Утверждение, отрицание и вопрос разделены там, где книга даёт их по отдельности; где справочник даёт их вместе (модальные глаголы старших классов) — одна подтема.
A12: «Кандидаты в вебинары»: по каждой группе — темы с красными подтемами (нет ни видео, ни материалов); отсортировано по классу, где тема появляется. Из них выбираем следующие вебинары.
A13: «Итоги»: сколько уроков сделать каждой группе, у скольких есть видео, сколько готово и опубликовано.
A15: Источник: грамматический справочник учебников (Use of English — оглавление и приложения). Подробный объём по строкам — в Spotlight_грамматика.xlsx.

Sheet Темы × классы
A1: № | B1: Блок | C1: Категория | D1: Тема | E1: Подтема (урок) | F1: Группы | G1: 3 кл. | H1: 4 кл. | I1: 5 кл. | J1: 6 кл. | K1: 7 кл. | L1: 8 кл. | M1: 9 кл. | N1: 10 кл. | O1: 11 кл. | P1: Видео 7–9 | Q1: Вебинар 7–9 (название / ссылка) | R1: Видео 10+ | S1: Вебинар 10+ (название / ссылка) | T1: Комментарий
A2: 1 | B2: Грамматика | C2: Глаголы: времена | D2: Past Simple | E2: Past Simple: правильные глаголы — утверждение (-ed) | F2: обе | G2: М4 · новое | H2: М6 · повт. | I2: М9 (9b) · повт. | J2: М7 (7a) · повт. | K2: М2 · повт. | L2: М1 (1c) · повт. | M2: М3 (3c) · повт. | N2: М5 (5c) · повт. | O2: М1 (1c) · повт. | P2: видео | Q2: Past Simple Regular+a funny story | R2: видео | S2: Past Tenses Review + travel and holidays Places to go.Past Simple regular verbs. (по названию)
A3: 2 | B3: Грамматика | C3: Глаголы: времена | D3: Past Simple | E3: Past Simple: правильные глаголы — отрицание (didn't + V) | F3: обе | G3: М4 · новое | H3: М6 · повт. | I3: М9 (9b) · повт. | J3: М7 (7a) · повт. | K3: М2 · повт. | L3: М1 (1c) · повт. | P3: видео | Q3: Past Simple regular questions and negatives | R3: нет
A4: 3 | B4: Грамматика | C4: Глаголы: времена | D4: Past Simple | E4: Past Simple: правильные глаголы — вопросы (Did …?) | F4: обе | G4: М4 · новое | H4: М6 · повт. | I4: М9 (9b) · повт. | J4: М7 (7a) · повт. | K4: М2 · повт. | L4: М1 (1c) · повт. | P4: видео | Q4: Past Simple regular questions and negatives | R4: нет
A5: 4 | B5: Грамматика | C5: Глаголы: времена | D5: Past Simple | E5: Past Simple: краткие ответы (Yes, I did / No, I didn't) | F5: обе | G5: М4 · новое | H5: М6 · повт. | I5: М9 (9b) · повт. М9 (9c) · повт. | J5: М7 (7a) · повт. М7 (7b) · повт. | K5: М2 · повт. | L5: М1 (1c) · повт. | P5: видео | Q5: Past Simple regular questions and negatives | R5: нет
A6: 5 | B6: Грамматика | C6: Глаголы: времена | D6: Past Simple | E6: Past Simple: орфография -ed | F6: обе | G6: М4 · новое | H6: М6 · повт. | I6: М9 (9b) · повт. | J6: М7 (7a) · повт. | K6: М2 · повт. | L6: М1 (1c) · расш. | M6: М3 (3c) · повт. | N6: М5 (5c) · повт. | O6: М1 (1c) · повт. | P6: вебинар | Q6: вебинар 19.11 (по расписанию): Past Simple: неправильные глаголы — отрицание и вопросы | R6: видео | S6: Places to go.Past Simple regular verbs. (по названию)
A7: 6 | B7: Грамматика | C7: Глаголы: времена | D7: Past Simple | E7: Past Simple: произношение -ed (/t/, /d/, /ɪd/) | F7: 7–9 | G7: М4 · новое | H7: М6 · повт. | P7: вебинар | Q7: вебинар 19.11 (по расписанию): Past Simple: неправильные глаголы — отрицание и вопросы | R7: —
A8: 7 | B8: Грамматика | C8: Глаголы: времена | D8: Past Simple | E8: Past Simple: неправильные глаголы — утверждение | F8: обе | G8: М5 · новое | H8: М7 · повт. | I8: М9 (9c) · расш. | J8: М7 (7b) · расш. | K8: М2 · повт. | L8: М1 (1c) · повт. | M8: М3 (3c) · повт. | N8: М5 (5c) · повт. | O8: М1 (1c) · повт. | P8: видео | Q8: Past Simple irregular verbs | R8: видео | S8: Movies+Irregular verbs Past Tenses Review + travel and holidays
A9: 8 | B9: Грамматика | C9: Глаголы: времена | D9: Past Simple | E9: Past Simple: неправильные глаголы — отрицание (didn't go) | F9: обе | G9: М5 · новое | H9: М7 · повт. | I9: М9 (9c) · повт. | J9: М7 (7b) · повт. | K9: М2 · повт. | P9: вебинар | Q9: вебинар 19.11 (по расписанию): Past Simple: неправильные глаголы — отрицание и вопросы | R9: нет
A10: 9 | B10: Грамматика | C10: Глаголы: времена | D10: Past Simple | E10: Past Simple: неправильные глаголы — вопросы (Did … go?) | F10: обе | G10: М5 · новое | H10: М7 · повт. | I10: М9 (9c) · повт. | J10: М7 (7b) · повт. | K10: М2 · повт. | P10: вебинар | Q10: вебинар 19.11 (по расписанию): Past Simple: неправильные глаголы — отрицание и вопросы | R10: нет
A11: 10 | B11: Грамматика | C11: Глаголы: времена | D11: Past Simple | E11: Past Simple: одна форма для всех лиц, исключение was/were | F11: 10+ | L11: М1 (1c) · новое | M11: М3 (3c) · повт. | N11: М5 (5c) · повт. | O11: М1 (1c) · повт. | P11: — | R11: видео | S11: Movies+Irregular verbs
A12: 11 | B12: Грамматика | C12: Глаголы: времена | D12: Past Simple | E12: Past Simple: значение — действие в прошлом (yesterday, ago) | F12: обе | G12: М4 · новое М5 · повт. | H12: М6 · повт. | I12: М9 (9b) · повт. | J12: М7 (7a) · повт. | K12: М2 · расш. | L12: М1 (1c) · повт. | M12: М3 (3c) · повт. | N12: М5 (5c) · повт. | O12: М1 (1c) · повт. | P12: видео | Q12: Past Simple Regular+a funny story Past Simple irregular verbs | R12: видео | S12: Movies+Irregular verbs Past Tenses Review + travel and holidays Places to go.Past Simple regular verbs. (по названию) Tense overview (Prese...mple, Present Perfect) Tenses overview 1
A13: 12 | B13: Грамматика | C13: Глаголы: времена | D13: Past Simple | E13: Past Simple: значение — действие в указанное время в прошлом | F13: 10+ | L13: М1 (1c) · новое | M13: М3 (3c) · повт. | N13: М5 (5c) · повт. | O13: М1 (1c) · повт. | P13: — | R13: видео | S13: Tense overview (Prese...mple, Present Perfect) Tenses overview 1
A14: 13 | B14: Грамматика | C14: Глаголы: времена | D14: Past Simple | E14: Past Simple: значение — повторяющиеся действия и привычки в прошлом | F14: 10+ | L14: М1 (1c) · новое | M14: М3 (3c) · повт. | N14: М5 (5c) · повт. | O14: М1 (1c) · повт. | P14: — | R14: нет
A15: 14 | B15: Грамматика | C15: Глаголы: времена | D15: Past Simple | E15: Past Simple: значение — последовательные действия | F15: 10+ | L15: М1 (1c) · новое | M15: М3 (3c) · повт. | N15: М5 (5c) · повт. | O15: М1 (1c) · повт. | P15: — | R15: вебинар | S15: вебинар 24.11 (по расписанию): Narrative tenses + history материалы: History + narrative tenses
A16: 15 | B16: Грамматика | C16: Глаголы: времена | D16: Past Simple | E16: Past Simple: значение — завершённые действия без связи с настоящим | F16: 10+ | M16: М3 (3c) · новое | N16: М5 (5c) · повт. | O16: М1 (1c) · повт. | P16: — | R16: нет
A17: 16 | B17: Грамматика | C17: Глаголы: времена | D17: Present Continuous | E17: Present Continuous: утверждение (am/is/are + V-ing) | F17: обе | G17: М7 · новое | H17: М1 · повт. | I17: М6 (6b) · повт. | J17: М5 (5a) · повт. | L17: М1 (1c) · повт. | M17: М1 (1c) · повт. | N17: М1 (1c) · повт. | O17: М1 (1c) · повт. | P17: видео | Q17: Favourite activities Present Cont Present Continuous+ activities | R17: нет
A18: 17 | B18: Грамматика | C18: Глаголы: времена | D18: Present Continuous | E18: Present Continuous: отрицание (I'm not / isn't / aren't) | F18: обе | G18: М7 · новое | H18: М1 · повт. | I18: М6 (6b) · повт. | J18: М5 (5b) · повт. | L18: М1 (1c) · повт. | P18: вебинар | Q18: вебинар 12.11 (по расписанию): Present Continuous: отрицание и вопросы материалы: Present Continuous questions and negatives | R18: нет
A19: 18 | B19: Грамматика | C19: Глаголы: времена | D19: Present Continuous | E19: Present Continuous: общие вопросы (Am/Is/Are …?) | F19: обе | G19: М7 · новое | H19: М1 · повт. | I19: М6 (6b) · повт. | J19: М5 (5b) · повт. | L19: М1 (1c) · повт. | P19: вебинар | Q19: вебинар 12.11 (по расписанию): Present Continuous: отрицание и вопросы материалы: Present Continuous questions and negatives | R19: нет
A20: 19 | B20: Грамматика | C20: Глаголы: времена | D20: Present Continuous | E20: Present Continuous: краткие ответы (Yes, I am / No, he isn't) | F20: обе | G20: М7 · новое | H20: М1 · повт. | I20: М6 (6b) · повт. | J20: М5 (5b) · повт. | L20: М1 (1c) · повт. | P20: вебинар | Q20: вебинар 12.11 (по расписанию): Present Continuous: отрицание и вопросы материалы: Present Continuous questions and negatives | R20: нет
A21: 20 | B21: Грамматика | C21: Глаголы: времена | D21: Present Continuous | E21: Present Continuous: орфография -ing | F21: 10+ | I21: М6 (6b) · новое | J21: М5 (5b) · повт. | L21: М1 (1c) · расш. | M21: М1 (1c) · повт. | N21: М1 (1c) · повт. | O21: М1 (1c) · повт. | P21: — | R21: нет
A22: 21 | B22: Грамматика | C22: Глаголы: времена | D22: Present Continuous | E22: Present Continuous: значение — действие сейчас (now) | F22: обе | G22: М7 · новое | H22: М1 · повт. | I22: М6 (6b) · повт. | J22: М5 (5b) · повт. | K22: М1 · повт. | L22: М1 (1c) · повт. | M22: М1 (1c) · повт. | N22: М1 (1c) · повт. | O22: М1 (1c) · повт. | P22: видео | Q22: Favourite activities Present Cont Present Continuous+ activities Present Simple vs Present Continuous | R22: видео | S22: Present tenses (review...cter and relationships
A23: 22 | B23: Грамматика | C23: Глаголы: времена | D23: Present Continuous | E23: Present Continuous: значение — действие в настоящий период (these days) | F23: 10+ | I23: М6 (6b) · новое | J23: М5 (5b) · расш. | K23: М1 · повт. | M23: М1 (1c) · повт. | N23: М1 (1c) · повт. | O23: М1 (1c) · повт. | P23: — | R23: видео | S23: Present tenses (review...cter and relationships
A24: 23 | B24: Грамматика | C24: Глаголы: времена | D24: Present Continuous | E24: Present Continuous: значение — запланированное будущее | F24: 10+ | J24: М5 (5b) · новое М10 (10b) · повт. | K24: М1 · повт. | L24: М1 (1c) · расш. | M24: М1 (1c) · повт. | N24: М1 (1c) · повт. | O24: М1 (1c) · повт. | P24: — | R24: видео | S24: Your schedule + Prese...ous for future meaning
A25: 24 | B25: Грамматика | C25: Глаголы: времена | D25: Present Continuous | E25: Present Continuous: значение — временные ситуации | F25: 10+ | L25: М1 (1c) · новое | M25: М1 (1c) · повт. | N25: М1 (1c) · повт. | O25: М1 (1c) · повт. | P25: — | R25: видео | S25: Present tenses (review...cter and relationships
A26: 25 | B26: Грамматика | C26: Глаголы: времена | D26: Present Continuous | E26: Present Continuous: значение — меняющиеся и развивающиеся ситуации | F26: 10+ | K26: М1 · новое | L26: М1 (1c) · повт. | M26: М1 (1c) · повт. | N26: М1 (1c) · повт. | O26: М1 (1c) · повт. | P26: — | R26: нет
A27: 26 | B27: Грамматика | C27: Глаголы: времена | D27: Present Continuous | E27: Present Continuous: значение — always + раздражение | F27: 10+ | K27: М1 · новое | L27: М1 (1c) · расш. | M27: М1 (1c) · повт. | N27: М1 (1c) · повт. | O27: М1 (1c) · повт. | P27: — | R27: нет
A28: 27 | B28: Грамматика | C28: Глаголы: времена | D28: Present Simple | E28: Present Simple: утверждение (I/you/we/they V, he/she/it V-s) | F28: обе | G28: М3 · новое | H28: М2 · повт. | I28: М5 (5a) · повт. | J28: М4 (4a) · повт. | L28: М1 (1c) · повт. | M28: М1 (1c) · повт. | N28: М1 (1c) · повт. | O28: М1 (1c) · повт. | P28: видео | Q28: Free time Like _ing | R28: нет
A29: 28 | B29: Грамматика | C29: Глаголы: времена | D29: Present Simple | E29: Present Simple: отрицание (don't/doesn't) | F29: обе | G29: М3 · новое | H29: М2 · повт. | I29: М5 (5b) · повт. | J29: М4 (4a) · повт. | L29: М1 (1c) · повт. | P29: видео | Q29: Free time Like _ing | R29: нет
A30: 29 | B30: Грамматика | C30: Глаголы: времена | D30: Present Simple | E30: Present Simple: общие вопросы (Do/Does …?) | F30: обе | G30: М3 · новое | H30: М2 · повт. | I30: М5 (5b) · повт. | J30: М4 (4a) · повт. | L30: М1 (1c) · повт. | P30: вебинар | Q30: вебинар 09.11 (по расписанию): Present Simple: вопросы и краткие ответы | R30: нет
A31: 30 | B31: Грамматика | C31: Глаголы: времена | D31: Present Simple | E31: Present Simple: краткие ответы (Yes, I do / No, he doesn't) | F31: обе | G31: М3 · новое | H31: М2 · повт. | I31: М5 (5b) · повт. | J31: М4 (4b) · повт. | L31: М1 (1c) · повт. | P31: вебинар | Q31: вебинар 09.11 (по расписанию): Present Simple: вопросы и краткие ответы | R31: нет
A32: 31 | B32: Грамматика | C32: Глаголы: времена | D32: Present Simple | E32: Present Simple: орфография окончания -s/-es (3 л. ед. ч.) | F32: обе | G32: М8 · новое | H32: М2 · повт. | I32: М5 (5a) · повт. | J32: М4 (4a) · повт. | L32: М1 (1c) · повт. | M32: М1 (1c) · повт. | N32: М1 (1c) · повт. | O32: М1 (1c) · повт. | P32: вебинар | Q32: вебинар 09.11 (по расписанию): Present Simple: вопросы и краткие ответы | R32: нет
A33: 32 | B33: Грамматика | C33: Глаголы: времена | D33: Present Simple | E33: Present Simple: произношение окончания -s/-es (/s/, /z/, /ɪz/) | F33: 7–9 | G33: М8 · новое | H33: М2 · повт. | P33: нет | R33: —
A34: 33 | B34: Грамматика | C34: Глаголы: времена | D34: Present Simple | E34: Present Simple: значение — регулярные действия, распорядок дня, привычки | F34: обе | G34: М3 · новое М8 · повт. | H34: М2 · расш. | I34: М5 (5a) · расш. | J34: М4 (4a) · расш. | K34: М1 · повт. | L34: М1 (1c) · повт. | M34: М1 (1c) · повт. | N34: М1 (1c) · повт. | O34: М1 (1c) · повт. | P34: видео | Q34: A day in my life+adver...ency in Present Simple Present Simple vs Present Continuous | R34: видео | S34: Daily Activities. Adverbs of Frequency in Pr.S. Tense overview (Prese...mple, Present Perfect) Tenses overview 1 Present tenses (review...cter and relationships
A35: 34 | B35: Грамматика | C35: Глаголы: времена | D35: Present Simple | E35: Present Simple: значение — постоянные состояния и действия | F35: 10+ | I35: М5 (5a) · новое | J35: М4 (4a) · повт. | K35: М1 · повт. | L35: М1 (1c) · повт. | M35: М1 (1c) · повт. | N35: М1 (1c) · повт. | O35: М1 (1c) · повт. | P35: — | R35: видео | S35: Present tenses (review...cter and relationships
A36: 35 | B36: Грамматика | C36: Глаголы: времена | D36: Present Simple | E36: Present Simple: значение — непреложные истины и законы природы | F36: 10+ | I36: М5 (5a) · новое | J36: М4 (4a) · повт. | K36: М1 · повт. | P36: — | R36: нет
A37: 36 | B37: Грамматика | C37: Глаголы: времена | D37: Present Simple | E37: Present Simple: значение — расписания и программы (будущее по расписанию) | F37: 10+ | K37: М1 · новое | L37: М1 (1c) · расш. | M37: М1 (1c) · повт. | N37: М1 (1c) · повт. | O37: М1 (1c) · повт. | P37: — | R37: видео | S37: Present Simple for shedules and timetables
A38: 37 | B38: Грамматика | C38: Глаголы: времена | D38: Present Simple | E38: Present Simple: значение — чувства и эмоции | F38: 10+ | K38: М1 · новое | P38: — | R38: нет
A39: 38 | B39: Грамматика | C39: Глаголы: времена | D39: Present Simple | E39: Present Simple: значение — обзоры, спортивные комментарии, повествование | F39: 10+ | K39: М1 · новое | M39: М1 (1c) · повт. | N39: М1 (1c) · повт. | O39: М1 (1c) · повт. | P39: — | R39: нет
A40: 39 | B40: Грамматика | C40: Глаголы: времена | D40: Present Simple | E40: Present Simple: значение — восклицания (Here comes …!) | F40: 10+ | M40: М1 (1c) · новое | N40: М1 (1c) · повт. | O40: М1 (1c) · повт. | P40: — | R40: нет
A41: 40 | B41: Грамматика | C41: Глаголы: времена | D41: Present Simple | E41: Present Simple: значение — последовательные действия в настоящем | F41: 10+ | L41: М1 (1c) · новое | P41: — | R41: нет
A42: 41 | B42: Грамматика | C42: Глаголы: времена | D42: Future Simple (will) | E42: Future Simple (will): утверждение (will/'ll + V) | F42: обе | H42: М8 · новое | I42: М10 (10b) · повт. | K42: М5 · повт. | L42: М1 (1c) · повт. | M42: М4 (4c) · повт. | N42: М3 (3c) · повт. | O42: М1 (1c) · повт. | P42: видео | Q42: Will(Future Simple)+weather,holiday items | R42: вебинар | S42: вебинар 06.11 (по расписанию): Will (Future Simple): формы и значения
A43: 42 | B43: Грамматика | C43: Глаголы: времена | D43: Future Simple (will) | E43: Future Simple (will): отрицание (will not/won't) | F43: обе | H43: М8 · новое | I43: М10 (10b) · повт. | P43: вебинар | Q43: вебинар 30.11 (по расписанию): Will: отрицание, вопросы, решения и обещания | R43: вебинар | S43: вебинар 06.11 (по расписанию): Will (Future Simple): формы и значения
A44: 43 | B44: Грамматика | C44: Глаголы: времена | D44: Future Simple (will) | E44: Future Simple (will): вопросы и краткие ответы | F44: обе | H44: М8 · новое | I44: М10 (10b) · повт. | P44: вебинар | Q44: вебинар 30.11 (по расписанию): Will: отрицание, вопросы, решения и обещания | R44: вебинар | S44: вебинар 06.11 (по расписанию): Will (Future Simple): формы и значения
A45: 44 | B45: Грамматика | C45: Глаголы: времена | D45: Future Simple (will) | E45: Future Simple (will): значение — предсказание/предположение | F45: обе | H45: М8 · новое | I45: М10 (10b) · расш. | K45: М5 · расш. | L45: М1 (1c) · расш. | M45: М4 (4c) · повт. | N45: М3 (3c) · повт. | O45: М1 (1c) · повт. | P45: видео | Q45: Will(Future Simple)+weather,holiday items | R45: видео | S45: Future tenses + school and jobs
A46: 45 | B46: Грамматика | C46: Глаголы: времена | D46: Future Simple (will) | E46: Future Simple (will): значение — решение в момент речи | F46: обе | H46: М8 · новое | I46: М10 (10b) · повт. | K46: М5 · повт. | L46: М1 (1c) · повт. | M46: М4 (4c) · повт. | N46: М3 (3c) · повт. | O46: М1 (1c) · повт. | P46: вебинар | Q46: вебинар 30.11 (по расписанию): Will: отрицание, вопросы, решения и обещания | R46: видео | S46: Future tenses + school and jobs
A47: 46 | B47: Грамматика | C47: Глаголы: времена | D47: Future Simple (will) | E47: Future Simple (will): значение — обещания | F47: обе | H47: М8 · новое | K47: М5 · повт. | L47: М1 (1c) · повт. | M47: М4 (4c) · повт. | N47: М3 (3c) · повт. | O47: М1 (1c) · повт. | P47: вебинар | Q47: вебинар 30.11 (по расписанию): Will: отрицание, вопросы, решения и обещания | R47: вебинар | S47: вебинар 06.11 (по расписанию): Will (Future Simple): формы и значения
A48: 47 | B48: Грамматика | C48: Глаголы: времена | D48: Future Simple (will) | E48: Future Simple (will): значение — просьбы (Will you…?) | F48: 10+ | I48: М10 (10b) · новое | K48: М5 · повт. | N48: М3 (3c) · повт. | O48: М1 (1c) · повт. | P48: — | R48: вебинар | S48: вебинар 06.11 (по расписанию): Will (Future Simple): формы и значения
A49: 48 | B49: Грамматика | C49: Глаголы: времена | D49: Future Simple (will) | E49: Future Simple (will): значение — угрозы и предупреждения | F49: 10+ | K49: М5 · новое | N49: М3 (3c) · повт. | O49: М1 (1c) · повт. | P49: — | R49: вебинар | S49: вебинар 06.11 (по расписанию): Will (Future Simple): формы и значения
A50: 49 | B50: Грамматика | C50: Глаголы: времена | D50: Future Simple (will) | E50: Future Simple (will): значение — надежды, страхи, предложения, комментарии | F50: 10+ | K50: М5 · новое | N50: М3 (3c) · расш. | O50: М1 (1c) · повт. | P50: — | R50: нет
A51: 50 | B51: Грамматика | C51: Глаголы: времена | D51: Future Simple (will) | E51: Future Simple (will): значение — неизбежные события (не зависят от нас) | F51: 10+ | K51: М5 · новое | P51: — | R51: нет
A52: 51 | B52: Грамматика | C52: Глаголы: времена | D52: Future Simple (will) | E52: Future Simple (will): значение — ещё не решили/не уверены (Maybe I'll…) | F52: 10+ | N52: М3 (3c) · новое | O52: М1 (1c) · повт. | P52: — | R52: вебинар | S52: вебинар 06.11 (по расписанию): Will (Future Simple): формы и значения
A53: 52 | B53: Грамматика | C53: Глаголы: времена | D53: Future Simple (will) | E53: Future Simple (will): Shall I/we? — предложение, просьба о совете | F53: 10+ | L53: М1 (1c) · новое | M53: М4 (4c) · повт. | N53: М3 (3c) · повт. | O53: М1 (1c) · повт. | P53: — | R53: вебинар | S53: вебинар 06.11 (по расписанию): Will (Future Simple): формы и значения
A54: 53 | B54: Грамматика | C54: Глаголы: времена | D54: Present Simple vs Present Continuous | E54: Present Simple vs Present Continuous: привычка vs сейчас | F54: обе | H54: М4 · новое | I54: М7 (7b) · повт. | J54: М6 (6b) · повт. М9 (9b) · повт. | K54: М1 · повт. | P54: видео | Q54: Present Simple vs Present Continuous | R54: видео | S54: Present Simple+Present Con-s+Clothes (по названию) Present Simple Present Continuous + Clothes (по названию)
A55: 54 | B55: Грамматика | C55: Глаголы: времена | D55: Present Simple vs Present Continuous | E55: Present Simple vs Present Continuous: постоянное состояние vs временная ситуация | F55: 10+ | I55: М7 (7b) · новое | J55: М6 (6b) · повт. М9 (9b) · повт. | L55: М1 (1c) · повт. | M55: М1 (1c) · повт. | N55: М1 (1c) · повт. | O55: М1 (1c) · повт. | P55: — | R55: нет
A56: 55 | B56: Грамматика | C56: Глаголы: времена | D56: Present Simple vs Present Continuous | E56: Present Simple vs Present Continuous: повторяющиеся действия vs настоящий период (these days) | F56: 10+ | K56: М1 · новое | L56: М1 (1c) · повт. | M56: М1 (1c) · повт. | N56: М1 (1c) · повт. | O56: М1 (1c) · повт. | P56: — | R56: нет
A57: 56 | B57: Грамматика | C57: Глаголы: времена | D57: Present Simple vs Present Continuous | E57: Present Simple vs Present Continuous: будущее — расписание vs договорённость | F57: 10+ | L57: М1 (1c) · новое | M57: М1 (1c) · повт. | P57: — | R57: нет
A58: 57 | B58: Грамматика | C58: Глаголы: времена | D58: be going to | E58: be going to: утверждение (am/is/are going to + V) | F58: обе | H58: М8 · новое | J58: М10 (10a) · повт. | L58: М1 (1c) · повт. | M58: М4 (4c) · повт. | N58: М3 (3c) · повт. | O58: М1 (1c) · повт. | P58: видео | Q58: Holidays+going to | R58: видео | S58: Plans for summer + Going to Plans for summer+to be going to
A59: 58 | B59: Грамматика | C59: Глаголы: времена | D59: be going to | E59: be going to: отрицание | F59: обе | H59: М8 · новое | J59: М10 (10a) · повт. | P59: вебинар | Q59: вебинар 26.11 (по расписанию): Be going to: отрицание и вопросы | R59: вебинар | S59: вебинар 10.11 (по расписанию): Be going to: отрицание, вопросы, предсказания материалы: Be going to предсказания с очевидным основанием
A60: 59 | B60: Грамматика | C60: Глаголы: времена | D60: be going to | E60: be going to: вопросы и краткие ответы | F60: обе | H60: М8 · новое | J60: М10 (10a) · расш. | P60: вебинар | Q60: вебинар 26.11 (по расписанию): Be going to: отрицание и вопросы | R60: вебинар | S60: вебинар 10.11 (по расписанию): Be going to: отрицание, вопросы, предсказания материалы: Be going to предсказания с очевидным основанием
A61: 60 | B61: Грамматика | C61: Глаголы: времена | D61: be going to | E61: be going to: значение — планы и намерения | F61: обе | H61: М8 · новое | I61: М10 (10b) · повт. | J61: М10 (10a) · повт. | K61: М5 · повт. | L61: М1 (1c) · повт. | M61: М4 (4c) · повт. | N61: М3 (3c) · повт. | O61: М1 (1c) · повт. | P61: видео | Q61: Holidays+going to | R61: видео | S61: Future tenses + school and jobs Plans for summer + Going to Plans for summer+to be going to
A62: 61 | B62: Грамматика | C62: Глаголы: времена | D62: be going to | E62: be going to: значение — уже принятое решение на ближайшее будущее | F62: 10+ | L62: М1 (1c) · новое | N62: М3 (3c) · повт. | P62: — | R62: вебинар | S62: вебинар 10.11 (по расписанию): Be going to: отрицание, вопросы, предсказания
A63: 62 | B63: Грамматика | C63: Глаголы: времена | D63: be going to | E63: be going to: значение — предсказание по очевидным признакам | F63: 10+ | J63: М10 (10a) · новое | K63: М5 · повт. | L63: М1 (1c) · повт. | M63: М4 (4c) · повт. | N63: М3 (3c) · повт. | O63: М1 (1c) · повт. | P63: — | R63: видео | S63: Future tenses + school and jobs
A64: 63 | B64: Грамматика | C64: Глаголы: времена | D64: be going to | E64: be going to vs will: план/признаки vs решение в момент речи/мнение | F64: 10+ | L64: М1 (1c) · новое | M64: М4 (4c) · повт. | N64: М3 (3c) · повт. | O64: М1 (1c) · повт. | P64: — | R64: видео | S64: Future tenses + school and jobs
A65: 64 | B65: Грамматика | C65: Глаголы: времена | D65: Present Perfect | E65: Present Perfect: утверждение (have/has + V3) | F65: 10+ | I65: М10 (10a) · новое | K65: М6 · повт. | L65: М2 (2c) · повт. | M65: М1 (1c) · повт. | N65: М1 (1c) · повт. | O65: М1 (1c) · повт. | P65: — | R65: видео | S65: Pr.Perfect already+just+yet+summer camp Present Perfect for since + experiences Present PerfectvsPast Simple+films Tense overview (Prese...mple, Present Perfect) Tenses overview 1 Shopping+Present Per...nt Perfect Continuous
A66: 65 | B66: Грамматика | C66: Глаголы: времена | D66: Present Perfect | E66: Present Perfect: отрицание (haven't/hasn't) | F66: 10+ | I66: М10 (10a) · новое | K66: М6 · повт. | P66: — | R66: видео | S66: Pr.Perfect already+just+yet+summer camp Present PerfectvsPast Simple+films
A67: 66 | B67: Грамматика | C67: Глаголы: времена | D67: Present Perfect | E67: Present Perfect: вопросы и краткие ответы | F67: 10+ | I67: М10 (10a) · новое | K67: М6 · повт. | P67: — | R67: видео | S67: Pr.Perfect already+just+yet+summer camp Present Perfect for since + experiences Present PerfectvsPast Simple+films
A68: 67 | B68: Грамматика | C68: Глаголы: времена | D68: Present Perfect | E68: Present Perfect: V3 правильных глаголов (-ed, орфография) | F68: 10+ | I68: М10 (10a) · новое | L68: М2 (2c) · повт. | M68: М1 (1c) · повт. | N68: М1 (1c) · повт. | O68: М1 (1c) · повт. | P68: — | R68: вебинар | S68: вебинар 17.11 (по расписанию): Present Perfect: Have you ever + неправильные глаголы
A69: 68 | B69: Грамматика | C69: Глаголы: времена | D69: Present Perfect | E69: Present Perfect: V3 неправильных глаголов | F69: 10+ | I69: М10 (10a) · новое | M69: М1 (1c) · повт. | N69: М1 (1c) · повт. | O69: М1 (1c) · повт. | P69: — | R69: вебинар | S69: вебинар 17.11 (по расписанию): Present Perfect: Have you ever + неправильные глаголы материалы: Holidays Have you ever; 10-12 Have you ever travelling
A70: 69 | B70: Грамматика | C70: Глаголы: времена | D70: Present Perfect | E70: Present Perfect: значение — жизненный опыт, перемены (ever/never) | F70: 10+ | I70: М10 (10a) · новое | K70: М6 · повт. | L70: М2 (2c) · расш. | M70: М1 (1c) · повт. | N70: М1 (1c) · повт. | O70: М1 (1c) · повт. | P70: — | R70: видео | S70: Present PerfectvsPast Simple+films Tense overview (Prese...mple, Present Perfect) Tenses overview 1
A71: 70 | B71: Грамматика | C71: Глаголы: времена | D71: Present Perfect | E71: Present Perfect: значение — результат в настоящем | F71: 10+ | I71: М10 (10a) · новое | K71: М6 · повт. | L71: М2 (2c) · повт. | M71: М1 (1c) · повт. | N71: М1 (1c) · повт. | O71: М1 (1c) · повт. | P71: — | R71: видео | S71: Present tenses (review...cter and relationships
A72: 71 | B72: Грамматика | C72: Глаголы: времена | D72: Present Perfect | E72: Present Perfect: значение — недавно завершённое действие (just) | F72: 10+ | L72: М2 (2c) · новое | M72: М1 (1c) · повт. | N72: М1 (1c) · повт. | O72: М1 (1c) · повт. | P72: — | R72: видео | S72: Pr.Perfect already+just+yet+summer camp
A73: 72 | B73: Грамматика | C73: Глаголы: времена | D73: Present Perfect | E73: Present Perfect: значение — неуказанное время в прошлом | F73: 10+ | K73: М6 · новое | M73: М1 (1c) · повт. | N73: М1 (1c) · повт. | O73: М1 (1c) · повт. | P73: — | R73: нет
A74: 73 | B74: Грамматика | C74: Глаголы: времена | D74: Present Perfect | E74: Present Perfect: значение — с прошлого до настоящего (stative verbs, for/since) | F74: 10+ | K74: М6 · новое | L74: М2 (2c) · повт. | M74: М1 (1c) · повт. | N74: М1 (1c) · повт. | O74: М1 (1c) · повт. | P74: — | R74: видео | S74: Present Perfect for since + experiences Tense overview (Prese...mple, Present Perfect) Tenses overview 1 Present tenses (review...cter and relationships
A75: 74 | B75: Грамматика | C75: Глаголы: времена | D75: Present Perfect | E75: Present Perfect: значение — незаконченный период (today, this week, so far) | F75: 10+ | L75: М2 (2c) · новое | M75: М1 (1c) · повт. | N75: М1 (1c) · повт. | O75: М1 (1c) · повт. | P75: — | R75: вебинар | S75: вебинар 17.11 (по расписанию): Present Perfect: Have you ever + неправильные глаголы
A76: 75 | B76: Грамматика | C76: Глаголы: времена | D76: Present Perfect | E76: Present Perfect: значение — акцент на количестве (seven times this week) | F76: 10+ | M76: М1 (1c) · новое | N76: М1 (1c) · повт. | O76: М1 (1c) · повт. | P76: — | R76: нет
A77: 76 | B77: Грамматика | C77: Глаголы: времена | D77: Present Perfect | E77: Present Perfect: слова-маркеры already / yet / just / ever / never | F77: 10+ | I77: М10 (10a) · новое | K77: М6 · расш. | L77: М2 (2c) · повт. | M77: М1 (1c) · повт. | N77: М1 (1c) · повт. | O77: М1 (1c) · повт. | P77: — | R77: видео | S77: Pr.Perfect already+just+yet+summer camp Present PerfectvsPast Simple+films Tense overview (Prese...mple, Present Perfect) Tenses overview 1
A78: 77 | B78: Грамматика | C78: Глаголы: времена | D78: Stative verbs | E78: Stative verbs: глаголы состояния не употребляются в Continuous | F78: 10+ | J78: М6 · новое | K78: М1 · повт. | L78: М1 (1c) · повт. | N78: М1 (1c) · повт. | O78: М1 (1c) · повт. | P78: — | R78: видео | S78: Stative verbs + perception and feelings Stative verbs.Preceive+feelings. Present tenses (review...cter and relationships
A79: 78 | B79: Грамматика | C79: Глаголы: времена | D79: Stative verbs | E79: Stative verbs: группы глаголов (восприятие, мышление, чувства, прочие) | F79: 10+ | K79: М1 · новое | L79: М1 (1c) · расш. | M79: М1 (1c) · повт. | N79: М1 (1c) · повт. | O79: М1 (1c) · повт. | P79: — | R79: видео | S79: Stative verbs + perception and feelings Stative verbs.Preceive+feelings.
A80: 79 | B80: Грамматика | C80: Глаголы: времена | D80: Stative verbs | E80: Stative verbs: разное значение в Simple и Continuous (think, have, see, taste…) | F80: 10+ | K80: М1 · новое | L80: М1 (1c) · повт. | M80: М1 (1c) · повт. | N80: М1 (1c) · повт. | O80: М1 (1c) · повт. | P80: — | R80: видео | S80: Stative verbs + perception and feelings Stative verbs.Preceive+feelings.
A81: 80 | B81: Грамматика | C81: Глаголы: времена | D81: Stative verbs | E81: Stative verbs: look, feel, hurt, ache — Simple = Continuous | F81: 10+ | K81: М1 · новое | L81: М1 (1c) · расш. | M81: М1 (1c) · повт. | N81: М1 (1c) · повт. | O81: М1 (1c) · повт. | P81: — | R81: нет
A82: 81 | B82: Грамматика | C82: Глаголы: времена | D82: Stative verbs | E82: Stative verbs: enjoy в Continuous — конкретное удовольствие | F82: 10+ | L82: М1 (1c) · новое | M82: М1 (1c) · повт. | N82: М1 (1c) · повт. | O82: М1 (1c) · повт. | P82: — | R82: нет
A83: 82 | B83: Грамматика | C83: Глаголы: времена | D83: Future forms (comparison) | E83: Future forms: Present Continuous — договорённости на ближайшее будущее | F83: 10+ | K83: М5 · новое | L83: М1 (1c) · повт. | M83: М4 (4c) · повт. | N83: М3 (3c) · повт. | O83: М1 (1c) · повт. | P83: — | R83: видео | S83: Future tenses + school and jobs Your schedule + Prese...ous for future meaning
A84: 83 | B84: Грамматика | C84: Глаголы: времена | D84: Future forms (comparison) | E84: Future forms: Present Simple — расписания и программы | F84: 10+ | K84: М5 · новое | L84: М1 (1c) · повт. | M84: М4 (4c) · повт. | N84: М3 (3c) · повт. | O84: М1 (1c) · повт. | P84: — | R84: видео | S84: Future tenses + school and jobs Present Simple for shedules and timetables
A85: 84 | B85: Грамматика | C85: Глаголы: времена | D85: Future forms (comparison) | E85: Future forms: will vs be going to — решение в момент речи vs план | F85: 10+ | K85: М5 · новое | L85: М1 (1c) · повт. | M85: М4 (4c) · повт. | N85: М3 (3c) · повт. | O85: М1 (1c) · повт. | P85: — | R85: видео | S85: Future tenses + school and jobs
A86: 85 | B86: Грамматика | C86: Глаголы: времена | D86: Future forms (comparison) | E86: Future forms: will vs be going to — прогноз-мнение vs прогноз по признакам | F86: 10+ | K86: М5 · новое | L86: М1 (1c) · повт. | M86: М4 (4c) · повт. | N86: М3 (3c) · повт. | O86: М1 (1c) · повт. | P86: — | R86: видео | S86: Future tenses + school and jobs
A87: 86 | B87: Грамматика | C87: Глаголы: времена | D87: Future forms (comparison) | E87: Future forms: обзор всех способов выражения будущего | F87: 10+ | K87: М5 · новое | L87: М1 (1c) · повт. | N87: М3 (3c) · повт. | O87: М1 (1c) · повт. | P87: — | R87: видео | S87: Future tenses + school and jobs
A88: 87 | B88: Грамматика | C88: Глаголы: времена | D88: Future forms (comparison) | E88: Future forms: Future Continuous/Future Perfect в системе будущих форм | F88: 10+ | M88: М4 (4c) · новое | O88: М1 (1c) · повт. | P88: — | R88: видео | S88: Future tenses + school and jobs
A89: 88 | B89: Грамматика | C89: Глаголы: времена | D89: Past Continuous | E89: Past Continuous: утверждение (was/were + V-ing) | F89: 10+ | L89: М1 (1c) · новое | M89: М3 (3c) · повт. | N89: М5 (5c) · повт. | O89: М1 (1c) · повт. | P89: — | R89: видео | S89: Past Continuous + news stories (по названию) Past Tenses Review + travel and holidays
A90: 89 | B90: Грамматика | C90: Глаголы: времена | D90: Past Continuous | E90: Past Continuous: значение — действие в процессе в момент прошлого | F90: 10+ | K90: М4 · новое | L90: М1 (1c) · повт. | M90: М3 (3c) · повт. | N90: М5 (5c) · повт. | O90: М1 (1c) · повт. | P90: — | R90: видео | S90: Past Continuous + news stories (по названию) Past Tenses Review + travel and holidays
A91: 90 | B91: Грамматика | C91: Глаголы: времена | D91: Past Continuous | E91: Past Continuous: значение — длительное действие, прерванное другим (when) | F91: 10+ | K91: М4 · новое | L91: М1 (1c) · повт. | M91: М3 (3c) · повт. | N91: М5 (5c) · повт. | O91: М1 (1c) · повт. | P91: — | R91: видео | S91: Past Continuous + news stories (по названию) Past Tenses Review + travel and holidays
A92: 91 | B92: Грамматика | C92: Глаголы: времена | D92: Past Continuous | E92: Past Continuous: значение — одновременные действия (while) | F92: 10+ | K92: М4 · новое | L92: М1 (1c) · повт. | M92: М3 (3c) · повт. | N92: М5 (5c) · повт. | O92: М1 (1c) · повт. | P92: — | R92: видео | S92: Past Continuous + news stories (по названию) Past Tenses Review + travel and holidays
A93: 92 | B93: Грамматика | C93: Глаголы: времена | D93: Past Continuous | E93: Past Continuous: значение — фон и атмосфера в рассказе | F93: 10+ | K93: М4 · новое | M93: М3 (3c) · повт. | N93: М5 (5c) · повт. | O93: М1 (1c) · повт. | P93: — | R93: видео | S93: Past Continuous + news stories (по названию) Past Tenses Review + travel and holidays
A94: 93 | B94: Грамматика | C94: Глаголы: времена | D94: Past Continuous | E94: Past Continuous: опущение второго was/were при одном подлежащем | F94: 10+ | K94: М4 · новое | P94: — | R94: нет
A95: 94 | B95: Грамматика | C95: Глаголы: времена | D95: Past Simple vs Past Continuous | E95: Past Simple vs Past Continuous: указанное время — завершённое vs в процессе | F95: 10+ | K95: М4 · новое | L95: М1 (1c) · повт. | M95: М3 (3c) · повт. | N95: М5 (5c) · повт. | O95: М1 (1c) · повт. | P95: — | R95: нет
A96: 95 | B96: Грамматика | C96: Глаголы: времена | D96: Past Simple vs Past Continuous | E96: Past Simple vs Past Continuous: последовательные vs одновременные действия | F96: 10+ | K96: М4 · новое | L96: М1 (1c) · повт. | M96: М3 (3c) · повт. | N96: М5 (5c) · повт. | O96: М1 (1c) · повт. | P96: — | R96: нет
A97: 96 | B97: Грамматика | C97: Глаголы: времена | D97: Past Simple vs Past Continuous | E97: Past Simple vs Past Continuous: прерванное (PC) и прерывающее (PS) действие | F97: 10+ | K97: М4 · новое | L97: М1 (1c) · повт. | M97: М3 (3c) · повт. | N97: М5 (5c) · повт. | O97: М1 (1c) · повт. | P97: — | R97: вебинар | S97: вебинар 27.10 (по расписанию): Tenses overview 2 материалы: Tenses overview 2
A98: 97 | B98: Грамматика | C98: Глаголы: времена | D98: Present Perfect Continuous | E98: Present Perfect Continuous: образование (have/has been + V-ing) | F98: 10+ | L98: М2 (2c) · новое | M98: М1 (1c) · повт. | N98: М1 (1c) · повт. | O98: М1 (1c) · повт. | P98: — | R98: видео | S98: Present Perfect Contin... eco-helping activities Shopping+Present Per...nt Perfect Continuous
A99: 98 | B99: Грамматика | C99: Глаголы: времена | D99: Present Perfect Continuous | E99: Present Perfect Continuous: значение — длительность до настоящего (since/for/how long) | F99: 10+ | K99: М8 · новое | L99: М2 (2c) · повт. | M99: М1 (1c) · повт. | N99: М1 (1c) · повт. | O99: М1 (1c) · повт. | P99: — | R99: видео | S99: Present Perfect Contin... eco-helping activities Present tenses (review...cter and relationships
A100: 99 | B100: Грамматика | C100: Глаголы: времена | D100: Present Perfect Continuous | E100: Present Perfect Continuous: значение — видимый результат длительного действия | F100: 10+ | K100: М8 · новое | L100: М2 (2c) · повт. | M100: М1 (1c) · повт. | N100: М1 (1c) · повт. | O100: М1 (1c) · повт. | P100: — | R100: видео | S100: Present Perfect Contin... eco-helping activities
...

Sheet Уроки
A1: № урока | B1: Группа | C1: Блок | D1: Тема | E1: Подтема (урок) | F1: Где используется (класс · модуль · статус) | G1: Папок | H1: Видео | I1: Вебинар | J1: Готовность | K1: Комментарий
A2: Мл-001 | B2: 7–9 | C2: Грамматика | D2: Past Simple | E2: Past Simple: правильные глаголы — утверждение (-ed) | F2: 3 кл. · М4 · новое 4 кл. · М6 · повт. | G2: 2 | H2: ='Темы × классы'!P2 | I2: ='Темы × классы'!Q2&"" | J2: не начат
A3: Мл-002 | B3: 7–9 | C3: Грамматика | D3: Past Simple | E3: Past Simple: правильные глаголы — отрицание (didn't + V) | F3: 3 кл. · М4 · новое 4 кл. · М6 · повт. | G3: 2 | H3: ='Темы × классы'!P3 | I3: ='Темы × классы'!Q3&"" | J3: не начат
A4: Мл-003 | B4: 7–9 | C4: Грамматика | D4: Past Simple | E4: Past Simple: правильные глаголы — вопросы (Did …?) | F4: 3 кл. · М4 · новое 4 кл. · М6 · повт. | G4: 2 | H4: ='Темы × классы'!P4 | I4: ='Темы × классы'!Q4&"" | J4: не начат
A5: Мл-004 | B5: 7–9 | C5: Грамматика | D5: Past Simple | E5: Past Simple: краткие ответы (Yes, I did / No, I didn't) | F5: 3 кл. · М4 · новое 4 кл. · М6 · повт. | G5: 2 | H5: ='Темы × классы'!P5 | I5: ='Темы × классы'!Q5&"" | J5: не начат
A6: Мл-005 | B6: 7–9 | C6: Грамматика | D6: Past Simple | E6: Past Simple: орфография -ed | F6: 3 кл. · М4 · новое 4 кл. · М6 · повт. | G6: 2 | H6: ='Темы × классы'!P6 | I6: ='Темы × классы'!Q6&"" | J6: не начат
A7: Мл-006 | B7: 7–9 | C7: Грамматика | D7: Past Simple | E7: Past Simple: произношение -ed (/t/, /d/, /ɪd/) | F7: 3 кл. · М4 · новое 4 кл. · М6 · повт. | G7: 2 | H7: ='Темы × классы'!P7 | I7: ='Темы × классы'!Q7&"" | J7: не начат
A8: Мл-007 | B8: 7–9 | C8: Грамматика | D8: Past Simple | E8: Past Simple: неправильные глаголы — утверждение | F8: 3 кл. · М5 · новое 4 кл. · М7 · повт. | G8: 2 | H8: ='Темы × классы'!P8 | I8: ='Темы × классы'!Q8&"" | J8: не начат
A9: Мл-008 | B9: 7–9 | C9: Грамматика | D9: Past Simple | E9: Past Simple: неправильные глаголы — отрицание (didn't go) | F9: 3 кл. · М5 · новое 4 кл. · М7 · повт. | G9: 2 | H9: ='Темы × классы'!P9 | I9: ='Темы × классы'!Q9&"" | J9: не начат
A10: Мл-009 | B10: 7–9 | C10: Грамматика | D10: Past Simple | E10: Past Simple: неправильные глаголы — вопросы (Did … go?) | F10: 3 кл. · М5 · новое 4 кл. · М7 · повт. | G10: 2 | H10: ='Темы × классы'!P10 | I10: ='Темы × классы'!Q10&"" | J10: не начат
A11: Мл-010 | B11: 7–9 | C11: Грамматика | D11: Past Simple | E11: Past Simple: значение — действие в прошлом (yesterday, ago) | F11: 3 кл. · М4 · новое 3 кл. · М5 · повт. 4 кл. · М6 · повт. | G11: 3 | H11: ='Темы × классы'!P12 | I11: ='Темы × классы'!Q12&"" | J11: не начат
A12: Мл-011 | B12: 7–9 | C12: Грамматика | D12: Present Continuous | E12: Present Continuous: утверждение (am/is/are + V-ing) | F12: 3 кл. · М7 · новое 4 кл. · М1 · повт. | G12: 2 | H12: ='Темы × классы'!P17 | I12: ='Темы × классы'!Q17&"" | J12: не начат
A13: Мл-012 | B13: 7–9 | C13: Грамматика | D13: Present Continuous | E13: Present Continuous: отрицание (I'm not / isn't / aren't) | F13: 3 кл. · М7 · новое 4 кл. · М1 · повт. | G13: 2 | H13: ='Темы × классы'!P18 | I13: ='Темы × классы'!Q18&"" | J13: не начат
A14: Мл-013 | B14: 7–9 | C14: Грамматика | D14: Present Continuous | E14: Present Continuous: общие вопросы (Am/Is/Are …?) | F14: 3 кл. · М7 · новое 4 кл. · М1 · повт. | G14: 2 | H14: ='Темы × классы'!P19 | I14: ='Темы × классы'!Q19&"" | J14: не начат
A15: Мл-014 | B15: 7–9 | C15: Грамматика | D15: Present Continuous | E15: Present Continuous: краткие ответы (Yes, I am / No, he isn't) | F15: 3 кл. · М7 · новое 4 кл. · М1 · повт. | G15: 2 | H15: ='Темы × классы'!P20 | I15: ='Темы × классы'!Q20&"" | J15: не начат
A16: Мл-015 | B16: 7–9 | C16: Грамматика | D16: Present Continuous | E16: Present Continuous: значение — действие сейчас (now) | F16: 3 кл. · М7 · новое 4 кл. · М1 · повт. | G16: 2 | H16: ='Темы × классы'!P22 | I16: ='Темы × классы'!Q22&"" | J16: не начат
A17: Мл-016 | B17: 7–9 | C17: Грамматика | D17: Present Simple | E17: Present Simple: утверждение (I/you/we/they V, he/she/it V-s) | F17: 3 кл. · М3 · новое 4 кл. · М2 · повт. | G17: 2 | H17: ='Темы × классы'!P28 | I17: ='Темы × классы'!Q28&"" | J17: не начат
A18: Мл-017 | B18: 7–9 | C18: Грамматика | D18: Present Simple | E18: Present Simple: отрицание (don't/doesn't) | F18: 3 кл. · М3 · новое 4 кл. · М2 · повт. | G18: 2 | H18: ='Темы × классы'!P29 | I18: ='Темы × классы'!Q29&"" | J18: не начат
A19: Мл-018 | B19: 7–9 | C19: Грамматика | D19: Present Simple | E19: Present Simple: общие вопросы (Do/Does …?) | F19: 3 кл. · М3 · новое 4 кл. · М2 · повт. | G19: 2 | H19: ='Темы × классы'!P30 | I19: ='Темы × классы'!Q30&"" | J19: не начат
A20: Мл-019 | B20: 7–9 | C20: Грамматика | D20: Present Simple | E20: Present Simple: краткие ответы (Yes, I do / No, he doesn't) | F20: 3 кл. · М3 · новое 4 кл. · М2 · повт. | G20: 2 | H20: ='Темы × классы'!P31 | I20: ='Темы × классы'!Q31&"" | J20: не начат
A21: Мл-020 | B21: 7–9 | C21: Грамматика | D21: Present Simple | E21: Present Simple: орфография окончания -s/-es (3 л. ед. ч.) | F21: 3 кл. · М8 · новое 4 кл. · М2 · повт. | G21: 2 | H21: ='Темы × классы'!P32 | I21: ='Темы × классы'!Q32&"" | J21: не начат
A22: Мл-021 | B22: 7–9 | C22: Грамматика | D22: Present Simple | E22: Present Simple: произношение окончания -s/-es (/s/, /z/, /ɪz/) | F22: 3 кл. · М8 · новое 4 кл. · М2 · повт. | G22: 2 | H22: ='Темы × классы'!P33 | I22: ='Темы × классы'!Q33&"" | J22: не начат
A23: Мл-022 | B23: 7–9 | C23: Грамматика | D23: Present Simple | E23: Present Simple: значение — регулярные действия, распорядок дня, привычки | F23: 3 кл. · М3 · новое 3 кл. · М8 · повт. 4 кл. · М2 · расш. | G23: 3 | H23: ='Темы × классы'!P34 | I23: ='Темы × классы'!Q34&"" | J23: не начат
A24: Мл-023 | B24: 7–9 | C24: Грамматика | D24: Future Simple (will) | E24: Future Simple (will): утверждение (will/'ll + V) | F24: 4 кл. · М8 · новое | G24: 1 | H24: ='Темы × классы'!P42 | I24: ='Темы × классы'!Q42&"" | J24: не начат
A25: Мл-024 | B25: 7–9 | C25: Грамматика | D25: Future Simple (will) | E25: Future Simple (will): отрицание (will not/won't) | F25: 4 кл. · М8 · новое | G25: 1 | H25: ='Темы × классы'!P43 | I25: ='Темы × классы'!Q43&"" | J25: не начат
A26: Мл-025 | B26: 7–9 | C26: Грамматика | D26: Future Simple (will) | E26: Future Simple (will): вопросы и краткие ответы | F26: 4 кл. · М8 · новое | G26: 1 | H26: ='Темы × классы'!P44 | I26: ='Темы × классы'!Q44&"" | J26: не начат
A27: Мл-026 | B27: 7–9 | C27: Грамматика | D27: Future Simple (will) | E27: Future Simple (will): значение — предсказание/предположение | F27: 4 кл. · М8 · новое | G27: 1 | H27: ='Темы × классы'!P45 | I27: ='Темы × классы'!Q45&"" | J27: не начат
A28: Мл-027 | B28: 7–9 | C28: Грамматика | D28: Future Simple (will) | E28: Future Simple (will): значение — решение в момент речи | F28: 4 кл. · М8 · новое | G28: 1 | H28: ='Темы × классы'!P46 | I28: ='Темы × классы'!Q46&"" | J28: не начат
A29: Мл-028 | B29: 7–9 | C29: Грамматика | D29: Future Simple (will) | E29: Future Simple (will): значение — обещания | F29: 4 кл. · М8 · новое | G29: 1 | H29: ='Темы × классы'!P47 | I29: ='Темы × классы'!Q47&"" | J29: не начат
A30: Мл-029 | B30: 7–9 | C30: Грамматика | D30: Present Simple vs Present Continuous | E30: Present Simple vs Present Continuous: привычка vs сейчас | F30: 4 кл. · М4 · новое | G30: 1 | H30: ='Темы × классы'!P54 | I30: ='Темы × классы'!Q54&"" | J30: не начат
A31: Мл-030 | B31: 7–9 | C31: Грамматика | D31: be going to | E31: be going to: утверждение (am/is/are going to + V) | F31: 4 кл. · М8 · новое | G31: 1 | H31: ='Темы × классы'!P58 | I31: ='Темы × классы'!Q58&"" | J31: не начат
A32: Мл-031 | B32: 7–9 | C32: Грамматика | D32: be going to | E32: be going to: отрицание | F32: 4 кл. · М8 · новое | G32: 1 | H32: ='Темы × классы'!P59 | I32: ='Темы × классы'!Q59&"" | J32: не начат
A33: Мл-032 | B33: 7–9 | C33: Грамматика | D33: be going to | E33: be going to: вопросы и краткие ответы | F33: 4 кл. · М8 · новое | G33: 1 | H33: ='Темы × классы'!P60 | I33: ='Темы × классы'!Q60&"" | J33: не начат
A34: Мл-033 | B34: 7–9 | C34: Грамматика | D34: be going to | E34: be going to: значение — планы и намерения | F34: 4 кл. · М8 · новое | G34: 1 | H34: ='Темы × классы'!P61 | I34: ='Темы × классы'!Q61&"" | J34: не начат
A35: Мл-034 | B35: 7–9 | C35: Грамматика | D35: can (ability) | E35: can (ability): значение — умение; утверждение can + глагол без to | F35: 3 кл. · М5 · новое | G35: 1 | H35: ='Темы × классы'!P125 | I35: ='Темы × классы'!Q125&"" | J35: не начат
A36: Мл-035 | B36: 7–9 | C36: Грамматика | D36: can (ability) | E36: can (ability): отрицание — cannot / can't | F36: 3 кл. · М5 · новое | G36: 1 | H36: ='Темы × классы'!P126 | I36: ='Темы × классы'!Q126&"" | J36: не начат
A37: Мл-036 | B37: 7–9 | C37: Грамматика | D37: can (ability) | E37: can (ability): вопросы и краткие ответы | F37: 3 кл. · М5 · новое | G37: 1 | H37: ='Темы × классы'!P127 | I37: ='Темы × классы'!Q127&"" | J37: не начат
A38: Мл-037 | B38: 7–9 | C38: Грамматика | D38: have got | E38: have got: утверждение — have got / has got (полные и краткие формы) | F38: 3 кл. · М5 · новое | G38: 1 | H38: ='Темы × классы'!P128 | I38: ='Темы × классы'!Q128&"" | J38: не начат
A39: Мл-038 | B39: 7–9 | C39: Грамматика | D39: have got | E39: have got: отрицание — haven't got / hasn't got | F39: 3 кл. · М5 · новое | G39: 1 | H39: ='Темы × классы'!P129 | I39: ='Темы × классы'!Q129&"" | J39: не начат
A40: Мл-039 | B40: 7–9 | C40: Грамматика | D40: have got | E40: have got: вопросы и краткие ответы | F40: 3 кл. · М5 · новое | G40: 1 | H40: ='Темы × классы'!P130 | I40: ='Темы × классы'!Q130&"" | J40: не начат
A41: Мл-040 | B41: 7–9 | C41: Грамматика | D41: have got | E41: have got: значение — принадлежность (иметь) | F41: 3 кл. · М5 · новое | G41: 1 | H41: ='Темы × классы'!P131 | I41: ='Темы × классы'!Q131&"" | J41: не начат
A42: Мл-041 | B42: 7–9 | C42: Грамматика | D42: have got | E42: have got: значение — описание внешности людей, животных, предметов | F42: 3 кл. · М5 · новое | G42: 1 | H42: ='Темы × классы'!P132 | I42: ='Темы × классы'!Q132&"" | J42: не начат
A43: Мл-042 | B43: 7–9 | C43: Грамматика | D43: have got | E43: have got: It's got (= It has got) vs It's (= It is) | F43: 3 кл. · М5 · новое | G43: 1 | H43: ='Темы × классы'!P134 | I43: ='Темы × классы'!Q134&"" | J43: не начат
A44: Мл-043 | B44: 7–9 | C44: Грамматика | D44: to be (Past: was/were) | E44: to be (Past): утверждение — was / were | F44: 3 кл. · М2 · новое 4 кл. · М5 · повт. | G44: 2 | H44: ='Темы × классы'!P135 | I44: ='Темы × классы'!Q135&"" | J44: не начат
A45: Мл-044 | B45: 7–9 | C45: Грамматика | D45: to be (Past: was/were) | E45: to be (Past): отрицание — wasn't / weren't | F45: 3 кл. · М2 · новое 4 кл. · М5 · повт. | G45: 2 | H45: ='Темы × классы'!P136 | I45: ='Темы × классы'!Q136&"" | J45: не начат
A46: Мл-045 | B46: 7–9 | C46: Грамматика | D46: to be (Past: was/were) | E46: to be (Past): вопросы и краткие ответы | F46: 3 кл. · М2 · новое 4 кл. · М5 · повт. | G46: 2 | H46: ='Темы × классы'!P137 | I46: ='Темы × классы'!Q137&"" | J46: не начат
A47: Мл-046 | B47: 7–9 | C47: Грамматика | D47: to be (Past: was/were) | E47: to be (Past): слова-указатели прошедшего времени | F47: 3 кл. · М2 · новое 4 кл. · М5 · повт. | G47: 2 | H47: ='Темы × классы'!P138 | I47: ='Темы × классы'!Q138&"" | J47: не начат
A48: Мл-047 | B48: 7–9 | C48: Грамматика | D48: to be (Present) | E48: to be (Present): утверждение — am/is/are, полные и краткие формы | F48: 3 кл. · М1 · новое | G48: 1 | H48: ='Темы × классы'!P139 | I48: ='Темы × классы'!Q139&"" | J48: не начат
A49: Мл-048 | B49: 7–9 | C49: Грамматика | D49: to be (Present) | E49: to be (Present): отрицание — am not / isn't / aren't | F49: 3 кл. · М1 · новое | G49: 1 | H49: ='Темы × классы'!P140 | I49: ='Темы × классы'!Q140&"" | J49: не начат
A50: Мл-049 | B50: 7–9 | C50: Грамматика | D50: to be (Present) | E50: to be (Present): вопросы и краткие ответы | F50: 3 кл. · М1 · новое | G50: 1 | H50: ='Темы × классы'!P141 | I50: ='Темы × классы'!Q141&"" | J50: не начат
A51: Мл-050 | B51: 7–9 | C51: Грамматика | D51: have to | E51: have to: значение — необходимость из-за обстоятельств (утверждение) | F51: 4 кл. · М2 · новое | G51: 1 | H51: ='Темы × классы'!P142 | I51: ='Темы × классы'!Q142&"" | J51: не начат
A52: Мл-051 | B52: 7–9 | C52: Грамматика | D52: have to | E52: have to: don't / doesn't have to — отсутствие необходимости | F52: 4 кл. · М2 · новое | G52: 1 | H52: ='Темы × классы'!P143 | I52: ='Темы × классы'!Q143&"" | J52: не начат
A53: Мл-052 | B53: 7–9 | C53: Грамматика | D53: have to | E53: have to: вопросы и краткие ответы — Do you have to…? | F53: 4 кл. · М2 · новое | G53: 1 | H53: ='Темы × классы'!P144 | I53: ='Темы × классы'!Q144&"" | J53: не начат
A54: Мл-053 | B54: 7–9 | C54: Грамматика | D54: may/might | E54: may/might: may — спросить разрешения (May I…?) и ответы | F54: 4 кл. · М3 · новое | G54: 1 | H54: ='Темы × классы'!P148 | I54: ='Темы × классы'!Q148&"" | J54: не начат
A55: Мл-054 | B55: 7–9 | C55: Грамматика | D55: must/mustn't | E55: must/mustn't: must — обязанность, необходимость | F55: 4 кл. · М4 · новое | G55: 1 | H55: ='Темы × классы'!P153 | I55: ='Темы × классы'!Q153&"" | J55: не начат
A56: Мл-055 | B56: 7–9 | C56: Грамматика | D56: must/mustn't | E56: must/mustn't: mustn't — запрет | F56: 4 кл. · М4 · новое | G56: 1 | H56: ='Темы × классы'!P154 | I56: ='Темы × классы'!Q154&"" | J56: не начат
A57: Мл-056 | B57: 7–9 | C57: Грамматика | D57: Countable / Uncountable nouns | E57: Countable / Uncountable: различие исчисляемых и неисчисляемых | F57: 3 кл. · М3 · новое 4 кл. · М3 · повт. | G57: 2 | H57: ='Темы × классы'!P330 | I57: ='Темы × классы'!Q330&"" | J57: не начат
A58: Мл-057 | B58: 7–9 | C58: Грамматика | D58: Plurals (irregular) | E58: Plurals (irregular): man — men, child — children, tooth — teeth, foot — feet, mouse — mice | F58: 3 кл. · М5 · новое | G58: 1 | H58: ='Темы × классы'!P343 | I58: ='Темы × классы'!Q343&"" | J58: не начат
A59: Мл-058 | B59: 7–9 | C59: Грамматика | D59: Plurals (irregular) | E59: Plurals (irregular): одинаковая форма ед. и мн. ч. (fish, sheep) | F59: 3 кл. · М5 · новое | G59: 1 | H59: ='Темы × классы'!P344 | I59: ='Темы × классы'!Q344&"" | J59: не начат
A60: Мл-059 | B60: 7–9 | C60: Грамматика | D60: Plurals (regular) | E60: Plurals (regular): основное правило — + -s | F60: 3 кл. · М2 · новое 3 кл. · М6 · повт. | G60: 2 | H60: ='Темы × классы'!P346 | I60: ='Темы × классы'!Q346&"" | J60: не начат
A61: Мл-060 | B61: 7–9 | C61: Грамматика | D61: Plurals (regular) | E61: Plurals (regular): орфография — + -es после -s, -ss, -sh, -ch, -x, -o | F61: 3 кл. · М6 · новое | G61: 1 | H61: ='Темы × классы'!P347 | I61: ='Темы × классы'!Q347&"" | J61: не начат
A62: Мл-061 | B62: 7–9 | C62: Грамматика | D62: Plurals (regular) | E62: Plurals (regular): орфография — -y → -ies (но гласная + y → -s) | F62: 3 кл. · М6 · новое | G62: 1 | H62: ='Темы × классы'!P348 | I62: ='Темы × классы'!Q348&"" | J62: не начат
A63: Мл-062 | B63: 7–9 | C63: Грамматика | D63: Plurals (regular) | E63: Plurals (regular): орфография — -f/-fe → -ves | F63: 3 кл. · М6 · новое | G63: 1 | H63: ='Темы × классы'!P349 | I63: ='Темы × классы'!Q349&"" | J63: не начат
A64: Мл-063 | B64: 7–9 | C64: Грамматика | D64: Possessive case ('s) | E64: Possessive case ('s): 's в ед. ч. — принадлежность | F64: 3 кл. · М4 · новое | G64: 1 | H64: ='Темы × классы'!P352 | I64: ='Темы × классы'!Q352&"" | J64: не начат
A65: Мл-064 | B65: 7–9 | C65: Грамматика | D65: Possessive case ('s) | E65: Possessive case ('s): вопрос Whose? | F65: 3 кл. · М4 · новое | G65: 1 | H65: ='Темы × классы'!P353 | I65: ='Темы × классы'!Q353&"" | J65: не начат
A66: Мл-065 | B66: 7–9 | C66: Грамматика | D66: a/an | E66: a/an: неопределённый артикль — только с исчисляемыми в ед. ч. | F66: 3 кл. · М4 · новое | G66: 1 | H66: ='Темы × классы'!P359 | I66: ='Темы × классы'!Q359&"" | J66: не начат
A67: Мл-066 | B67: 7–9 | C67: Грамматика | D67: a/an | E67: a/an: a перед согласной, an перед гласной | F67: 3 кл. · М4 · новое | G67: 1 | H67: ='Темы × классы'!P360 | I67: ='Темы × классы'!Q360&"" | J67: не начат
A68: Мл-067 | B68: 7–9 | C68: Грамматика | D68: a/an/some/any | E68: a/an/some/any: some — в утверждениях (неисчисляемые и мн. ч.) | F68: 3 кл. · М3 · новое | G68: 1 | H68: ='Темы × классы'!P361 | I68: ='Темы × классы'!Q361&"" | J68: не начат
A69: Мл-068 | B69: 7–9 | C69: Грамматика | D69: a/an/some/any | E69: a/an/some/any: any — в отрицаниях | F69: 3 кл. · М3 · новое | G69: 1 | H69: ='Темы × классы'!P362 | I69: ='Темы × классы'!Q362&"" | J69: не начат
A70: Мл-069 | B70: 7–9 | C70: Грамматика | D70: a/an/some/any | E70: a/an/some/any: any — в вопросах | F70: 3 кл. · М3 · новое | G70: 1 | H70: ='Темы × классы'!P363 | I70: ='Темы × классы'!Q363&"" | J70: не начат
A71: Мл-070 | B71: 7–9 | C71: Грамматика | D71: a/an/some/any | E71: a/an/some/any: some в вопросах — просьба и предложение | F71: 3 кл. · М3 · новое | G71: 1 | H71: ='Темы × классы'!P364 | I71: ='Темы × классы'!Q364&"" | J71: не начат
A72: Мл-071 | B72: 7–9 | C72: Грамматика | D72: much/many/a lot of | E72: much/many/a lot of: a lot of / lots of — в утверждениях (исчисляемые и неисчисляемые) | F72: 4 кл. · М3 · новое | G72: 1 | H72: ='Темы × классы'!P367 | I72: ='Темы × классы'!Q367&"" | J72: не начат
A73: Мл-072 | B73: 7–9 | C73: Грамматика | D73: much/many/a lot of | E73: much/many/a lot of: much/many — отрицание | F73: 4 кл. · М3 · новое | G73: 1 | H73: ='Темы × классы'!P368 | I73: ='Темы × классы'!Q368&"" | J73: не начат
A74: Мл-073 | B74: 7–9 | C74: Грамматика | D74: much/many/a lot of | E74: much/many/a lot of: much/many — вопросы | F74: 4 кл. · М3 · новое | G74: 1 | H74: ='Темы × классы'!P369 | I74: ='Темы × классы'!Q369&"" | J74: не начат
A75: Мл-074 | B75: 7–9 | C75: Грамматика | D75: much/many/a lot of | E75: much/many/a lot of: How much? / How many? | F75: 4 кл. · М3 · новое | G75: 1 | H75: ='Темы × классы'!P370 | I75: ='Темы × классы'!Q370&"" | J75: не начат
A76: Мл-075 | B76: 7–9 | C76: Грамматика | D76: much/many/a lot of | E76: much/many/a lot of: краткие ответы и a lot / lots без существительного | F76: 4 кл. · М3 · новое | G76: 1 | H76: ='Темы × классы'!P371 | I76: ='Темы × классы'!Q371&"" | J76: не начат
A77: Мл-076 | B77: 7–9 | C77: Грамматика | D77: Demonstratives (this/that/these/those) | E77: Demonstratives: this — these (ед. и мн. ч.) | F77: 3 кл. · М4 · новое | G77: 1 | H77: ='Темы × классы'!P402 | I77: ='Темы × классы'!Q402&"" | J77: не начат
A78: Мл-077 | B78: 7–9 | C78: Грамматика | D78: Demonstratives (this/that/these/those) | E78: Demonstratives: that — those (ед. и мн. ч.) | F78: 3 кл. · М4 · новое | G78: 1 | H78: ='Темы × классы'!P403 | I78: ='Темы × классы'!Q403&"" | J78: не начат
A79: Мл-078 | B79: 7–9 | C79: Грамматика | D79: Demonstratives (this/that/these/those) | E79: Demonstratives: this/these vs that/those — близко vs далеко | F79: 3 кл. · М4 · новое | G79: 1 | H79: ='Темы × классы'!P404 | I79: ='Темы × классы'!Q404&"" | J79: не начат
A80: Мл-079 | B80: 7–9 | C80: Грамматика | D80: Possessive adjectives | E80: Possessive adjectives: формы my, your, his, her, its, our, their | F80: 3 кл. · М2 · новое | G80: 1 | H80: ='Темы × классы'!P405 | I80: ='Темы × классы'!Q405&"" | J80: не начат
A81: Мл-080 | B81: 7–9 | C81: Грамматика | D81: Possessive adjectives | E81: Possessive adjectives: значение — принадлежность и отношения между людьми | F81: 3 кл. · М2 · новое | G81: 1 | H81: ='Темы × классы'!P406 | I81: ='Темы × классы'!Q406&"" | J81: не начат
A82: Мл-081 | B82: 7–9 | C82: Грамматика | D82: Adverbs of frequency | E82: Adverbs of frequency: значение — never, sometimes, usually, often, always | F82: 4 кл. · М2 · новое | G82: 1 | H82: ='Темы × классы'!P445 | I82: ='Темы × классы'!Q445&"" | J82: не начат
A83: Мл-082 | B83: 7–9 | C83: Грамматика | D83: Adverbs of frequency | E83: Adverbs of frequency: место — перед смысловым глаголом, после be | F83: 4 кл. · М2 · новое | G83: 1 | H83: ='Темы × классы'!P446 | I83: ='Темы × классы'!Q446&"" | J83: не начат
A84: Мл-083 | B84: 7–9 | C84: Грамматика | D84: Comparatives & Superlatives | E84: Comparatives & Superlatives: сравнительная степень — -er + than | F84: 4 кл. · М4 · новое | G84: 1 | H84: ='Темы × классы'!P450 | I84: ='Темы × классы'!Q450&"" | J84: не начат
A85: Мл-084 | B85: 7–9 | C85: Грамматика | D85: Comparatives & Superlatives | E85: Comparatives & Superlatives: сравнительная степень — more (многосложные) | F85: 4 кл. · М4 · новое | G85: 1 | H85: ='Темы × классы'!P451 | I85: ='Темы × классы'!Q451&"" | J85: не начат
A86: Мл-085 | B86: 7–9 | C86: Грамматика | D86: Comparatives & Superlatives | E86: Comparatives & Superlatives: орфография -er/-est (удвоение, -e, y → i) | F86: 4 кл. · М4 · новое 4 кл. · М7 · расш. | G86: 2 | H86: ='Темы × классы'!P452 | I86: ='Темы × классы'!Q452&"" | J86: не начат
A87: Мл-086 | B87: 7–9 | C87: Грамматика | D87: Comparatives & Superlatives | E87: Comparatives & Superlatives: превосходная степень — the -est + of/in | F87: 4 кл. · М7 · новое | G87: 1 | H87: ='Темы × классы'!P453 | I87: ='Темы × классы'!Q453&"" | J87: не начат
A88: Мл-087 | B88: 7–9 | C88: Грамматика | D88: Comparatives & Superlatives | E88: Comparatives & Superlatives: превосходная степень — the most | F88: 4 кл. · М7 · новое | G88: 1 | H88: ='Темы × классы'!P454 | I88: ='Темы × классы'!Q454&"" | J88: не начат
A89: Мл-088 | B89: 7–9 | C89: Грамматика | D89: Comparatives & Superlatives | E89: Comparatives & Superlatives: неправильные прилагательные (good, bad, many/much, little) | F89: 4 кл. · М7 · новое | G89: 1 | H89: ='Темы × классы'!P455 | I89: ='Темы × классы'!Q455&"" | J89: не начат
A90: Мл-089 | B90: 7–9 | C90: Грамматика | D90: Comparatives & Superlatives | E90: Comparatives & Superlatives: двусложные на -y/-er/-ow — -er/-est | F90: 4 кл. · М4 · новое 4 кл. · М7 · повт. | G90: 2 | H90: ='Темы × классы'!P456 | I90: ='Темы × классы'!Q456&"" | J90: не начат
A91: Мл-090 | B91: 7–9 | C91: Грамматика | D91: Ordinal numbers | E91: Ordinal numbers: first, second, third и составные (21st, 22nd) | F91: 4 кл. · М5 · новое | G91: 1 | H91: ='Темы × классы'!P489 | I91: ='Темы × классы'!Q489&"" | J91: не начат
A92: Мл-091 | B92: 7–9 | C92: Грамматика | D92: Ordinal numbers | E92: Ordinal numbers: образование с -th и орфография (fifth, ninth, twelfth, twentieth) | F92: 4 кл. · М5 · новое | G92: 1 | H92: ='Темы × классы'!P490 | I92: ='Темы × классы'!Q490&"" | J92: не начат
A93: Мл-092 | B93: 7–9 | C93: Грамматика | D93: Ordinal numbers | E93: Ordinal numbers: с артиклем the и даты | F93: 4 кл. · М5 · новое | G93: 1 | H93: ='Темы × классы'!P491 | I93: ='Темы × классы'!Q491&"" | J93: не начат
A94: Мл-093 | B94: 7–9 | C94: Грамматика | D94: Prepositions of place | E94: Prepositions of place: in, on, under | F94: 3 кл. · М6 · новое 4 кл. · М1 · повт. | G94: 2 | H94: ='Темы × классы'!P492 | I94: ='Темы × классы'!Q492&"" | J94: не начат
A95: Мл-094 | B95: 7–9 | C95: Грамматика | D95: Prepositions of place | E95: Prepositions of place: next to, in front of, behind | F95: 3 кл. · М6 · новое 4 кл. · М1 · повт. | G95: 2 | H95: ='Темы × классы'!P493 | I95: ='Темы × классы'!Q493&"" | J95: не начат
A96: Мл-095 | B96: 7–9 | C96: Грамматика | D96: Prepositions of place | E96: Prepositions of place: opposite, between | F96: 4 кл. · М1 · новое | G96: 1 | H96: ='Темы × классы'!P494 | I96: ='Темы × классы'!Q494&"" | J96: не начат
A97: Мл-096 | B97: 7–9 | C97: Грамматика | D97: Prepositions of time | E97: Prepositions of time: at — время, праздники, at night/at noon/at the weekend | F97: 3 кл. · М8 · новое | G97: 1 | H97: ='Темы × классы'!P500 | I97: ='Темы × классы'!Q500&"" | J97: не начат
A98: Мл-097 | B98: 7–9 | C98: Грамматика | D98: Prepositions of time | E98: Prepositions of time: on — дни недели и праздничные дни | F98: 3 кл. · М8 · новое | G98: 1 | H98: ='Темы × классы'!P501 | I98: ='Темы × классы'!Q501&"" | J98: не начат
A99: Мл-098 | B99: 7–9 | C99: Грамматика | D99: Prepositions of time | E99: Prepositions of time: in — части суток (in the morning/afternoon/evening) | F99: 3 кл. · М8 · новое | G99: 1 | H99: ='Темы × классы'!P503 | I99: ='Темы × классы'!Q503&"" | J99: не начат
A100: Мл-099 | B100: 7–9 | C100: Грамматика | D100: Question words | E100: Question words: Whose? — чья вещь | F100: 3 кл. · М4 · новое | G100: 1 | H100: ='Темы × классы'!P509 | I100: ='Темы × классы'!Q509&"" | J100: не начат
...

Sheet Папки уроков
A1: Класс | B1: Модуль | C1: Урок учебника | D1: Тема (папка) | E1: Подтема (урок) | F1: № урока | G1: В учебнике | H1: Что именно в этом классе | I1: Группа | J1: Видео | K1: Готовность | L1: Путь
A2: 3 | B2: Module 1 · School days | D2: to be (Present) | E2: to be (Present): утверждение — am/is/are, полные и краткие формы | F2: Мл-047 | G2: новое | H2: все лица; I am/I'm, he is/he's, we are/we're… | I2: 7–9 | J2: =IFERROR(INDEX('Уроки'!$H:$H,MATCH(F2,'Уроки'!$A:$A,0)),"") | K2: =IFERROR(INDEX('Уроки'!$J:$J,MATCH(F2,'Уроки'!$A:$A,0)),"") | L2: Spotlight / 3 класс / Module 1 · School days / to be (Present) / to be (Present): утверждение — am/is/are, полные и краткие формы
A3: 3 | B3: Module 1 · School days | D3: to be (Present) | E3: to be (Present): отрицание — am not / isn't / aren't | F3: Мл-048 | G3: новое | H3: полные и краткие: I'm not, isn't, aren't | I3: 7–9 | J3: =IFERROR(INDEX('Уроки'!$H:$H,MATCH(F3,'Уроки'!$A:$A,0)),"") | K3: =IFERROR(INDEX('Уроки'!$J:$J,MATCH(F3,'Уроки'!$A:$A,0)),"") | L3: Spotlight / 3 класс / Module 1 · School days / to be (Present) / to be (Present): отрицание — am not / isn't / aren't
A4: 3 | B4: Module 1 · School days | D4: to be (Present) | E4: to be (Present): вопросы и краткие ответы | F4: Мл-049 | G4: новое | H4: Am I? Is he? Are you?; Yes, I am / No, I'm not | I4: 7–9 | J4: =IFERROR(INDEX('Уроки'!$H:$H,MATCH(F4,'Уроки'!$A:$A,0)),"") | K4: =IFERROR(INDEX('Уроки'!$J:$J,MATCH(F4,'Уроки'!$A:$A,0)),"") | L4: Spotlight / 3 класс / Module 1 · School days / to be (Present) / to be (Present): вопросы и краткие ответы
A5: 3 | B5: Module 2 · Family moments | D5: to be (Past: was/were) | E5: to be (Past): утверждение — was / were | F5: Мл-043 | G5: новое | H5: I/he/she/it was; you/we/they were | I5: 7–9 | J5: =IFERROR(INDEX('Уроки'!$H:$H,MATCH(F5,'Уроки'!$A:$A,0)),"") | K5: =IFERROR(INDEX('Уроки'!$J:$J,MATCH(F5,'Уроки'!$A:$A,0)),"") | L5: Spotlight / 3 класс / Module 2 · Family moments / to be (Past: was/were) / to be (Past): утверждение — was / were
A6: 3 | B6: Module 2 · Family moments | D6: to be (Past: was/were) | E6: to be (Past): отрицание — wasn't / weren't | F6: Мл-044 | G6: новое | H6: полные и краткие: was not/wasn't, were not/weren't | I6: 7–9 | J6: =IFERROR(INDEX('Уроки'!$H:$H,MATCH(F6,'Уроки'!$A:$A,0)),"") | K6: =IFERROR(INDEX('Уроки'!$J:$J,MATCH(F6,'Уроки'!$A:$A,0)),"") | L6: Spotlight / 3 класс / Module 2 · Family moments / to be (Past: was/were) / to be (Past): отрицание — wasn't / weren't
A7: 3 | B7: Module 2 · Family moments | D7: to be (Past: was/were) | E7: to be (Past): вопросы и краткие ответы | F7: Мл-045 | G7: новое | H7: was/were перед подлежащим; Yes, I was / No, they weren't | I7: 7–9 | J7: =IFERROR(INDEX('Уроки'!$H:$H,MATCH(F7,'Уроки'!$A:$A,0)),"") | K7: =IFERROR(INDEX('Уроки'!$J:$J,MATCH(F7,'Уроки'!$A:$A,0)),"") | L7: Spotlight / 3 класс / Module 2 · Family moments / to be (Past: was/were) / to be (Past): вопросы и краткие ответы
A8: 3 | B8: Module 2 · Family moments | D8: to be (Past: was/were) | E8: to be (Past): слова-указатели прошедшего времени | F8: Мл-046 | G8: новое | H8: yesterday, last week/month/year, two days ago, in 1975 | I8: 7–9 | J8: =IFERROR(INDEX('Уроки'!$H:$H,MATCH(F8,'Уроки'!$A:$A,0)),"") | K8: =IFERROR(INDEX('Уроки'!$J:$J,MATCH(F8,'Уроки'!$A:$A,0)),"") | L8: Spotlight / 3 класс / Module 2 · Family moments / to be (Past: was/were) / to be (Past): слова-указатели прошедшего времени
A9: 3 | B9: Module 2 · Family moments | D9: Plurals (regular) | E9: Plurals (regular): основное правило — + -s | F9: Мл-059 | G9: новое | H9: только это правило: pen — pens, book — books | I9: 7–9 | J9: =IFERROR(INDEX('Уроки'!$H:$H,MATCH(F9,'Уроки'!$A:$A,0)),"") | K9: =IFERROR(INDEX('Уроки'!$J:$J,MATCH(F9,'Уроки'!$A:$A,0)),"") | L9: Spotlight / 3 класс / Module 2 · Family moments / Plurals (regular) / Plurals (regular): основное правило — + -s
A10: 3 | B10: Module 2 · Family moments | D10: Possessive adjectives | E10: Possessive adjectives: формы my, your, his, her, its, our, their | F10: Мл-079 | G10: новое | H10: полная таблица I — my … they — their | I10: 7–9 | J10: =IFERROR(INDEX('Уроки'!$H:$H,MATCH(F10,'Уроки'!$A:$A,0)),"") | K10: =IFERROR(INDEX('Уроки'!$J:$J,MATCH(F10,'Уроки'!$A:$A,0)),"") | L10: Spotlight / 3 класс / Module 2 · Family moments / Possessive adjectives / Possessive adjectives: формы my, your, his, her, its, our, their
A11: 3 | B11: Module 2 · Family moments | D11: Possessive adjectives | E11: Possessive adjectives: значение — принадлежность и отношения между людьми | F11: Мл-080 | G11: новое | H11: перед существительным: This is my mother | I11: 7–9 | J11: =IFERROR(INDEX('Уроки'!$H:$H,MATCH(F11,'Уроки'!$A:$A,0)),"") | K11: =IFERROR(INDEX('Уроки'!$J:$J,MATCH(F11,'Уроки'!$A:$A,0)),"") | L11: Spotlight / 3 класс / Module 2 · Family moments / Possessive adjectives / Possessive adjectives: значение — принадлежность и отношения между людьми
A12: 3 | B12: Module 3 · All the things I like! | D12: Present Simple | E12: Present Simple: утверждение (I/you/we/they V, he/she/it V-s) | F12: Мл-016 | G12: новое | H12: все лица: I like, he/she/it likes | I12: 7–9 | J12: =IFERROR(INDEX('Уроки'!$H:$H,MATCH(F12,'Уроки'!$A:$A,0)),"") | K12: =IFERROR(INDEX('Уроки'!$J:$J,MATCH(F12,'Уроки'!$A:$A,0)),"") | L12: Spotlight / 3 класс / Module 3 · All the things I like! / Present Simple / Present Simple: утверждение (I/you/we/they V, he/she/it V-s)
A13: 3 | B13: Module 3 · All the things I like! | D13: Present Simple | E13: Present Simple: отрицание (don't/doesn't) | F13: Мл-017 | G13: новое | H13: do not/don't, does not/doesn't | I13: 7–9 | J13: =IFERROR(INDEX('Уроки'!$H:$H,MATCH(F13,'Уроки'!$A:$A,0)),"") | K13: =IFERROR(INDEX('Уроки'!$J:$J,MATCH(F13,'Уроки'!$A:$A,0)),"") | L13: Spotlight / 3 класс / Module 3 · All the things I like! / Present Simple / Present Simple: отрицание (don't/doesn't)
... A24: 3 | B24: Module 4 · Come in and play! | D24: Past Simple | E24: Past Simple: правильные глаголы — вопросы (Did …?) | F24: Мл-003 | G24: новое | H24: Did … work? | I24: 7–9 | J24: =IFERROR(INDEX('Уроки'!$H:$H,MATCH(F24,'Уроки'!$A:$A,0)),"") | K24: =IFERROR(INDEX('Уроки'!$J:$J,MATCH(F24,'Уроки'!$A:$A,0)),"") | L24: Spotlight / 3 класс / Module 4 · Come in and play! / Past Simple / Past Simple: правильные глаголы — вопросы (Did …?)
A25: 3 | B25: Module 4 · Come in and play! | D25: Past Simple | E25: Past Simple: краткие ответы (Yes, I did / No, I didn't) | F25: Мл-004 | G25: новое | I25: 7–9 | J25: =IFERROR(INDEX('Уроки'!$H:$H,MATCH(F25,'Уроки'!$A:$A,0)),"") | K25: =IFERROR(INDEX('Уроки'!$J:$J,MATCH(F25,'Уроки'!$A:$A,0)),"") | L25: Spotlight / 3 класс / Module 4 · Come in and play! / Past Simple / Past Simple: краткие ответы (Yes, I did / No, I didn't)
A26: 3 | B26: Module 4 · Come in and play! | D26: Past Simple | E26: Past Simple: орфография -ed | F26: Мл-005 | G26: новое | H26: danced, studied, travelled, planned | I26: 7–9 | J26: =IFERROR(INDEX('Уроки'!$H:$H,MATCH(F26,'Уроки'!$A:$A,0)),"") | K26: =IFERROR(INDEX('Уроки'!$J:$J,MATCH(F26,'Уроки'!$A:$A,0)),"") | L26: Spotlight / 3 класс / Module 4 · Come in and play! / Past Simple / Past Simple: орфография -ed
A27: 3 | B27: Module 4 · Come in and play! | D27: Past Simple | E27: Past Simple: произношение -ed (/t/, /d/, /ɪd/) | F27: Мл-006 | G27: новое | H27: washed /t/, played /d/, wanted /ɪd/ | I27: 7–9 | J27: =IFERROR(INDEX('Уроки'!$H:$H,MATCH(F27,'Уроки'!$A:$A,0)),"") | K27: =IFERROR(INDEX('Уроки'!$J:$J,MATCH(F27,'Уроки'!$A:$A,0)),"") | L27: Spotlight / 3 класс / Module 4 · Come in and play! / Past Simple / Past Simple: произношение -ed (/t/, /d/, /ɪd/)
A28: 3 | B28: Module 4 · Come in and play! | D28: Past Simple | E28: Past Simple: значение — действие в прошлом (yesterday, ago) | F28: Мл-010 | G28: новое | H28: yesterday, last week/month/year, two days ago, in 1975 | I28: 7–9 | J28: =IFERROR(INDEX('Уроки'!$H:$H,MATCH(F28,'Уроки'!$A:$A,0)),"") | K28: =IFERROR(INDEX('Уроки'!$J:$J,MATCH(F28,'Уроки'!$A:$A,0)),"") | L28: Spotlight / 3 класс / Module 4 · Come in and play! / Past Simple / Past Simple: значение — действие в прошлом (yesterday, ago)
A29: 3 | B29: Module 4 · Come in and play! | D29: Possessive case ('s) | E29: Possessive case ('s): 's в ед. ч. — принадлежность | F29: Мл-063 | G29: новое | H29: Lulu's rocking horse, the dog's house; только ед. ч. | I29: 7–9 | J29: =IFERROR(INDEX('Уроки'!$H:$H,MATCH(F29,'Уроки'!$A:$A,0)),"") | K29: =IFERROR(INDEX('Уроки'!$J:$J,MATCH(F29,'Уроки'!$A:$A,0)),"") | L29: Spotlight / 3 класс / Module 4 · Come in and play! / Possessive case ('s) / Possessive case ('s): 's в ед. ч. — принадлежность
A30: 3 | B30: Module 4 · Come in and play! | D30: Possessive case ('s) | E30: Possessive case ('s): вопрос Whose? | F30: Мл-064 | G30: новое | H30: кому принадлежит | I30: 7–9 | J30: =IFERROR(INDEX('Уроки'!$H:$H,MATCH(F30,'Уроки'!$A:$A,0)),"") | K30: =IFERROR(INDEX('Уроки'!$J:$J,MATCH(F30,'Уроки'!$A:$A,0)),"") | L30: Spotlight / 3 класс / Module 4 · Come in and play! / Possessive case ('s) / Possessive case ('s): вопрос Whose?
A31: 3 | B31: Module 4 · Come in and play! | D31: a/an | E31: a/an: неопределённый артикль — только с исчисляемыми в ед. ч. | F31: Мл-065 | G31: новое | H31: the не дан | I31: 7–9 | J31: =IFERROR(INDEX('Уроки'!$H:$H,MATCH(F31,'Уроки'!$A:$A,0)),"") | K31: =IFERROR(INDEX('Уроки'!$J:$J,MATCH(F31,'Уроки'!$A:$A,0)),"") | L31: Spotlight / 3 класс / Module 4 · Come in and play! / a/an / a/an: неопределённый артикль — только с исчисляемыми в ед. ч.
A32: 3 | B32: Module 4 · Come in and play! | D32: a/an | E32: a/an: a перед согласной, an перед гласной | F32: Мл-066 | G32: новое | H32: a ball, an elephant | I32: 7–9 | J32: =IFERROR(INDEX('Уроки'!$H:$H,MATCH(F32,'Уроки'!$A:$A,0)),"") | K32: =IFERROR(INDEX('Уроки'!$J:$J,MATCH(F32,'Уроки'!$A:$A,0)),"") | L32: Spotlight / 3 класс / Module 4 · Come in and play! / a/an / a/an: a перед согласной, an перед гласной
A33: 3 | B33: Module 4 · Come in and play! | D33: Demonstratives (this/that/these/those) | E33: Demonstratives: this — these (ед. и мн. ч.) | F33: Мл-076 | G33: новое | I33: 7–9 | J33: =IFERROR(INDEX('Уроки'!$H:$H,MATCH(F33,'Уроки'!$A:$A,0)),"") | K33: =IFERROR(INDEX('Уроки'!$J:$J,MATCH(F33,'Уроки'!$A:$A,0)),"") | L33: Spotlight / 3 класс / Module 4 · Come in and play! / Demonstratives (this/that/these/those) / Demonstratives: this — these (ед. и мн. ч.)
A34: 3 | B34: Module 4 · Come in and play! | D34: Demonstratives (this/that/these/those) | E34: Demonstratives: that — those (ед. и мн. ч.) | F34: Мл-077 | G34: новое | I34: 7–9 | J34: =IFERROR(INDEX('Уроки'!$H:$H,MATCH(F34,'Уроки'!$A:$A,0)),"") | K34: =IFERROR(INDEX('Уроки'!$J:$J,MATCH(F34,'Уроки'!$A:$A,0)),"") | L34: Spotlight / 3 класс / Module 4 · Come in and play! / Demonstratives (this/that/these/those) / Demonstratives: that — those (ед. и мн. ч.)
A35: 3 | B35: Module 4 · Come in and play! | D35: Demonstratives (this/that/these/those) | E35: Demonstratives: this/these vs that/those — близко vs далеко | F35: Мл-078 | G35: новое | H35: о людях, животных, предметах рядом / далеко | I35: 7–9 | J35: =IFERROR(INDEX('Уроки'!$H:$H,MATCH(F35,'Уроки'!$A:$A,0)),"") | K35: =IFERROR(INDEX('Уроки'!$J:$J,MATCH(F35,'Уроки'!$A:$A,0)),"") | L35: Spotlight / 3 класс / Module 4 · Come in and play! / Demonstratives (this/that/these/those) / Demonstratives: this/these vs that/those — близко vs далеко
A36: 3 | B36: Module 4 · Come in and play! | D36: Question words | E36: Question words: Whose? — чья вещь | F36: Мл-099 | G36: новое | H36: только whose (Whose is this doll?), в разделе Possessive case | I36: 7–9 | J36: =IFERROR(INDEX('Уроки'!$H:$H,MATCH(F36,'Уроки'!$A:$A,0)),"") | K36: =IFERROR(INDEX('Уроки'!$J:$J,MATCH(F36,'Уроки'!$A:$A,0)),"") | L36: Spotlight / 3 класс / Module 4 · Come in and play! / Question words / Question words: Whose? — чья вещь
A37: 3 | B37: Module 5 · Furry friends! | D37: Past Simple | E37: Past Simple: неправильные глаголы — утверждение | F37: Мл-007 | G37: новое | H37: 8 глаголов: say–said, tell–told, go–went, come–came, see–saw, find–found, get–got, have–had (+ make–made) | I37: 7–9 | J37: =IFERROR(INDEX('Уроки'!$H:$H,MATCH(F37,'Уроки'!$A:$A,0)),"") | K37: =IFERROR(INDEX('Уроки'!$J:$J,MATCH(F37,'Уроки'!$A:$A,0)),"") | L37: Spotlight / 3 класс / Module 5 · Furry friends! / Past Simple / Past Simple: неправильные глаголы — утверждение
A38: 3 | B38: Module 5 · Furry friends! | D38: Past Simple | E38: Past Simple: неправильные глаголы — отрицание (didn't go) | F38: Мл-008 | G38: новое | H38: didn't see | I38: 7–9 | J38: =IFERROR(INDEX('Уроки'!$H:$H,MATCH(F38,'Уроки'!$A:$A,0)),"") | K38: =IFERROR(INDEX('Уроки'!$J:$J,MATCH(F38,'Уроки'!$A:$A,0)),"") | L38: Spotlight / 3 класс / Module 5 · Furry friends! / Past Simple / Past Simple: неправильные глаголы — отрицание (didn't go)
A39: 3 | B39: Module 5 · Furry friends! | D39: Past Simple | E39: Past Simple: неправильные глаголы — вопросы (Did … go?) | F39: Мл-009 | G39: новое | H39: Did he go …? | I39: 7–9 | J39: =IFERROR(INDEX('Уроки'!$H:$H,MATCH(F39,'Уроки'!$A:$A,0)),"") | K39: =IFERROR(INDEX('Уроки'!$J:$J,MATCH(F39,'Уроки'!$A:$A,0)),"") | L39: Spotlight / 3 класс / Module 5 · Furry friends! / Past Simple / Past Simple: неправильные глаголы — вопросы (Did … go?)
A40: 3 | B40: Module 5 · Furry friends! | D40: Past Simple | E40: Past Simple: значение — действие в прошлом (yesterday, ago) | F40: Мл-010 | G40: повторение | I40: 7–9 | J40: =IFERROR(INDEX('Уроки'!$H:$H,MATCH(F40,'Уроки'!$A:$A,0)),"") | K40: =IFERROR(INDEX('Уроки'!$J:$J,MATCH(F40,'Уроки'!$A:$A,0)),"") | L40: Spotlight / 3 класс / Module 5 · Furry friends! / Past Simple / Past Simple: значение — действие в прошлом (yesterday, ago)
A41: 3 | B41: Module 5 · Furry friends! | D41: can (ability) | E41: can (ability): значение — умение; утверждение can + глагол без to | F41: Мл-034 | G41: новое | H41: все лица; способность, умение | I41: 7–9 | J41: =IFERROR(INDEX('Уроки'!$H:$H,MATCH(F41,'Уроки'!$A:$A,0)),"") | K41: =IFERROR(INDEX('Уроки'!$J:$J,MATCH(F41,'Уроки'!$A:$A,0)),"") | L41: Spotlight / 3 класс / Module 5 · Furry friends! / can (ability) / can (ability): значение — умение; утверждение can + глагол без to
A42: 3 | B42: Module 5 · Furry friends! | D42: can (ability) | E42: can (ability): отрицание — cannot / can't | F42: Мл-035 | G42: новое | H42: cannot (полное), can't (краткое) | I42: 7–9 | J42: =IFERROR(INDEX('Уроки'!$H:$H,MATCH(F42,'Уроки'!$A:$A,0)),"") | K42: =IFERROR(INDEX('Уроки'!$J:$J,MATCH(F42,'Уроки'!$A:$A,0)),"") | L42: Spotlight / 3 класс / Module 5 · Furry friends! / can (ability) / can (ability): отрицание — cannot / can't
A43: 3 | B43: Module 5 · Furry friends! | D43: can (ability) | E43: can (ability): вопросы и краткие ответы | F43: Мл-036 | G43: новое | H43: Yes, I can / No, he can't | I43: 7–9 | J43: =IFERROR(INDEX('Уроки'!$H:$H,MATCH(F43,'Уроки'!$A:$A,0)),"") | K43: =IFERROR(INDEX('Уроки'!$J:$J,MATCH(F43,'Уроки'!$A:$A,0)),"") | L43: Spotlight / 3 класс / Module 5 · Furry friends! / can (ability) / can (ability): вопросы и краткие ответы
A44: 3 | B44: Module 5 · Furry friends! | D44: have got | E44: have got: утверждение — have got / has got (полные и краткие формы) | F44: Мл-037 | G44: новое | H44: все лица, полные и краткие (I've got, he's got) | I44: 7–9 | J44: =IFERROR(INDEX('Уроки'!$H:$H,MATCH(F44,'Уроки'!$A:$A,0)),"") | K44: =IFERROR(INDEX('Уроки'!$J:$J,MATCH(F44,'Уроки'!$A:$A,0)),"") | L44: Spotlight / 3 класс / Module 5 · Furry friends! / have got / have got: утверждение — have got / has got (полные и краткие формы)
A45: 3 | B45: Module 5 · Furry friends! | D45: have got | E45: have got: отрицание — haven't got / hasn't got | F45: Мл-038 | G45: новое | H45: полные и краткие | I45: 7–9 | J45: =IFERROR(INDEX('Уроки'!$H:$H,MATCH(F45,'Уроки'!$A:$A,0)),"") | K45: =IFERROR(INDEX('Уроки'!$J:$J,MATCH(F45,'Уроки'!$A:$A,0)),"") | L45: Spotlight / 3 класс / Module 5 · Furry friends! / have got / have got: отрицание — haven't got / hasn't got
A46: 3 | B46: Module 5 · Furry friends! | D46: have got | E46: have got: вопросы и краткие ответы | F46: Мл-039 | G46: новое | H46: Have you got…? Has he got…?; got в ответе опускается | I46: 7–9 | J46: =IFERROR(INDEX('Уроки'!$H:$H,MATCH(F46,'Уроки'!$A:$A,0)),"") | K46: =IFERROR(INDEX('Уроки'!$J:$J,MATCH(F46,'Уроки'!$A:$A,0)),"") | L46: Spotlight / 3 класс / Module 5 · Furry friends! / have got / have got: вопросы и краткие ответы
A47: 3 | B47: Module 5 · Furry friends! | D47: have got | E47: have got: значение — принадлежность (иметь) | F47: Мл-040 | G47: новое | H47: She has got a rabbit | I47: 7–9 | J47: =IFERROR(INDEX('Уроки'!$H:$H,MATCH(F47,'Уроки'!$A:$A,0)),"") | K47: =IFERROR(INDEX('Уроки'!$J:$J,MATCH(F47,'Уроки'!$A:$A,0)),"") | L47: Spotlight / 3 класс / Module 5 · Furry friends! / have got / have got: значение — принадлежность (иметь)
A48: 3 | B48: Module 5 · Furry friends! | D48: have got | E48: have got: значение — описание внешности людей, животных, предметов | F48: Мл-041 | G48: новое | H48: It's got a big mouth | I48: 7–9 | J48: =IFERROR(INDEX('Уроки'!$H:$H,MATCH(F48,'Уроки'!$A:$A,0)),"") | K48: =IFERROR(INDEX('Уроки'!$J:$J,MATCH(F48,'Уроки'!$A:$A,0)),"") | L48: Spotlight / 3 класс / Module 5 · Furry friends! / have got / have got: значение — описание внешности людей, животных, предметов
A49: 3 | B49: Module 5 · Furry friends! | D49: have got | E49: have got: It's got (= It has got) vs It's (= It is) | F49: Мл-042 | G49: новое | H49: It's got = It has got; It's = It is | I49: 7–9 | J49: =IFERROR(INDEX('Уроки'!$H:$H,MATCH(F49,'Уроки'!$A:$A,0)),"") | K49: =IFERROR(INDEX('Уроки'!$J:$J,MATCH(F49,'Уроки'!$A:$A,0)),"") | L49: Spotlight / 3 класс / Module 5 · Furry friends! / have got / have got: It's got (= It has got) vs It's (= It is)
A50: 3 | B50: Module 5 · Furry friends! | D50: Plurals (irregular) | E50: Plurals (irregular): man — men, child — children, tooth — teeth, foot — feet, mouse — mice | F50: Мл-057 | G50: новое | H50: + woman — women | I50: 7–9 | J50: =IFERROR(INDEX('Уроки'!$H:$H,MATCH(F50,'Уроки'!$A:$A,0)),"") | K50: =IFERROR(INDEX('Уроки'!$J:$J,MATCH(F50,'Уроки'!$A:$A,0)),"") | L50: Spotlight / 3 класс / Module 5 · Furry friends! / Plurals (irregular) / Plurals (irregular): man — men, child — children, tooth — teeth, foot — feet, mouse — mice
A51: 3 | B51: Module 5 · Furry friends! | D51: Plurals (irregular) | E51: Plurals (irregular): одинаковая форма ед. и мн. ч. (fish, sheep) | F51: Мл-058 | G51: новое | H51: fish — fish, sheep — sheep | I51: 7–9 | J51: =IFERROR(INDEX('Уроки'!$H:$H,MATCH(F51,'Уроки'!$A:$A,0)),"") | K51: =IFERROR(INDEX('Уроки'!$J:$J,MATCH(F51,'Уроки'!$A:$A,0)),"") | L51: Spotlight / 3 класс / Module 5 · Furry friends! / Plurals (irregular) / Plurals (irregular): одинаковая форма ед. и мн. ч. (fish, sheep)
A52: 3 | B52: Module 6 · Home, sweet home! | D52: Plurals (regular) | E52: Plurals (regular): основное правило — + -s | F52: Мл-059 | G52: повторение | H52: chair — chairs | I52: 7–9 | J52: =IFERROR(INDEX('Уроки'!$H:$H,MATCH(F52,'Уроки'!$A:$A,0)),"") | K52: =IFERROR(INDEX('Уроки'!$J:$J,MATCH(F52,'Уроки'!$A:$A,0)),"") | L52: Spotlight / 3 класс / Module 6 · Home, sweet home! / Plurals (regular) / Plurals (regular): основное правило — + -s
... A56: 3 | B56: Module 6 · Home, sweet home! | D56: Prepositions of place | E56: Prepositions of place: in, on, under | F56: Мл-093 | G56: новое | H56: схемами | I56: 7–9 | J56: =IFERROR(INDEX('Уроки'!$H:$H,MATCH(F56,'Уроки'!$A:$A,0)),"") | K56: =IFERROR(INDEX('Уроки'!$J:$J,MATCH(F56,'Уроки'!$A:$A,0)),"") | L56: Spotlight / 3 класс / Module 6 · Home, sweet home! / Prepositions of place / Prepositions of place: in, on, under
A57: 3 | B57: Module 6 · Home, sweet home! | D57: Prepositions of place | E57: Prepositions of place: next to, in front of, behind | F57: Мл-094 | G57: новое | I57: 7–9 | J57: =IFERROR(INDEX('Уроки'!$H:$H,MATCH(F57,'Уроки'!$A:$A,0)),"") | K57: =IFERROR(INDEX('Уроки'!$J:$J,MATCH(F57,'Уроки'!$A:$A,0)),"") | L57: Spotlight / 3 класс / Module 6 · Home, sweet home! / Prepositions of place / Prepositions of place: next to, in front of, behind
A58: 3 | B58: Module 6 · Home, sweet home! | D58: There is / There are | E58: There is / There are: there is — утверждение (ед. ч.) | F58: Мл-102 | G58: новое | H58: there's — краткая форма | I58: 7–9 | J58: =IFERROR(INDEX('Уроки'!$H:$H,MATCH(F58,'Уроки'!$A:$A,0)),"") | K58: =IFERROR(INDEX('Уроки'!$J:$J,MATCH(F58,'Уроки'!$A:$A,0)),"") | L58: Spotlight / 3 класс / Module 6 · Home, sweet home! / There is / There are / There is / There are: there is — утверждение (ед. ч.)
A59: 3 | B59: Module 6 · Home, sweet home! | D59: There is / There are | E59: There is / There are: there are — утверждение (мн. ч.) | F59: Мл-103 | G59: новое | H59: There are two beds… | I59: 7–9 | J59: =IFERROR(INDEX('Уроки'!$H:$H,MATCH(F59,'Уроки'!$A:$A,0)),"") | K59: =IFERROR(INDEX('Уроки'!$J:$J,MATCH(F59,'Уроки'!$A:$A,0)),"") | L59: Spotlight / 3 класс / Module 6 · Home, sweet home! / There is / There are / There is / There are: there are — утверждение (мн. ч.)
A60: 3 | B60: Module 6 · Home, sweet home! | D60: There is / There are | E60: There is / There are: отрицание — there isn't / there aren't | F60: Мл-104 | G60: новое | H60: There isn't / There aren't | I60: 7–9 | J60: =IFERROR(INDEX('Уроки'!$H:$H,MATCH(F60,'Уроки'!$A:$A,0)),"") | K60: =IFERROR(INDEX('Уроки'!$J:$J,MATCH(F60,'Уроки'!$A:$A,0)),"") | L60: Spotlight / 3 класс / Module 6 · Home, sweet home! / There is / There are / There is / There are: отрицание — there isn't / there aren't
A61: 3 | B61: Module 6 · Home, sweet home! | D61: There is / There are | E61: There is / There are: вопросы — Is there…? / Are there…? | F61: Мл-105 | G61: новое | H61: Is there…? / Are there…? (кратких ответов нет) | I61: 7–9 | J61: =IFERROR(INDEX('Уроки'!$H:$H,MATCH(F61,'Уроки'!$A:$A,0)),"") | K61: =IFERROR(INDEX('Уроки'!$J:$J,MATCH(F61,'Уроки'!$A:$A,0)),"") | L61: Spotlight / 3 класс / Module 6 · Home, sweet home! / There is / There are / There is / There are: вопросы — Is there…? / Are there…?
A62: 3 | B62: Module 7 · A day off! | D62: Present Continuous | E62: Present Continuous: утверждение (am/is/are + V-ing) | F62: Мл-011 | G62: новое | H62: полная и краткая: I am/I'm playing | I62: 7–9 | J62: =IFERROR(INDEX('Уроки'!$H:$H,MATCH(F62,'Уроки'!$A:$A,0)),"") | K62: =IFERROR(INDEX('Уроки'!$J:$J,MATCH(F62,'Уроки'!$A:$A,0)),"") | L62: Spotlight / 3 класс / Module 7 · A day off! / Present Continuous / Present Continuous: утверждение (am/is/are + V-ing)
A63: 3 | B63: Module 7 · A day off! | D63: Present Continuous | E63: Present Continuous: отрицание (I'm not / isn't / aren't) | F63: Мл-012 | G63: новое | H63: am not, isn't, aren't | I63: 7–9 | J63: =IFERROR(INDEX('Уроки'!$H:$H,MATCH(F63,'Уроки'!$A:$A,0)),"") | K63: =IFERROR(INDEX('Уроки'!$J:$J,MATCH(F63,'Уроки'!$A:$A,0)),"") | L63: Spotlight / 3 класс / Module 7 · A day off! / Present Continuous / Present Continuous: отрицание (I'm not / isn't / aren't)
A64: 3 | B64: Module 7 · A day off! | D64: Present Continuous | E64: Present Continuous: общие вопросы (Am/Is/Are …?) | F64: Мл-013 | G64: новое | H64: Am I / Is he / Are you …? | I64: 7–9 | J64: =IFERROR(INDEX('Уроки'!$H:$H,MATCH(F64,'Уроки'!$A:$A,0)),"") | K64: =IFERROR(INDEX('Уроки'!$J:$J,MATCH(F64,'Уроки'!$A:$A,0)),"") | L64: Spotlight / 3 класс / Module 7 · A day off! / Present Continuous / Present Continuous: общие вопросы (Am/Is/Are …?)
A65: 3 | B65: Module 7 · A day off! | D65: Present Continuous | E65: Present Continuous: краткие ответы (Yes, I am / No, he isn't) | F65: Мл-014 | G65: новое | H65: все лица; -ing-глагол опускается | I65: 7–9 | J65: =IFERROR(INDEX('Уроки'!$H:$H,MATCH(F65,'Уроки'!$A:$A,0)),"") | K65: =IFERROR(INDEX('Уроки'!$J:$J,MATCH(F65,'Уроки'!$A:$A,0)),"") | L65: Spotlight / 3 класс / Module 7 · A day off! / Present Continuous / Present Continuous: краткие ответы (Yes, I am / No, he isn't)
A66: 3 | B66: Module 7 · A day off! | D66: Present Continuous | E66: Present Continuous: значение — действие сейчас (now) | F66: Мл-015 | G66: новое | H66: now, at the moment | I66: 7–9 | J66: =IFERROR(INDEX('Уроки'!$H:$H,MATCH(F66,'Уроки'!$A:$A,0)),"") | K66: =IFERROR(INDEX('Уроки'!$J:$J,MATCH(F66,'Уроки'!$A:$A,0)),"") | L66: Spotlight / 3 класс / Module 7 · A day off! / Present Continuous / Present Continuous: значение — действие сейчас (now)
A67: 3 | B67: Module 8 · Day by day | D67: Present Simple | E67: Present Simple: орфография окончания -s/-es (3 л. ед. ч.) | F67: Мл-020 | G67: новое | H67: +s; -ss/-sh/-ch/-x/-o +es; согласная+y → -ies; play – plays | I67: 7–9 | J67: =IFERROR(INDEX('Уроки'!$H:$H,MATCH(F67,'Уроки'!$A:$A,0)),"") | K67: =IFERROR(INDEX('Уроки'!$J:$J,MATCH(F67,'Уроки'!$A:$A,0)),"") | L67: Spotlight / 3 класс / Module 8 · Day by day / Present Simple / Present Simple: орфография окончания -s/-es (3 л. ед. ч.)
A68: 3 | B68: Module 8 · Day by day | D68: Present Simple | E68: Present Simple: произношение окончания -s/-es (/s/, /z/, /ɪz/) | F68: Мл-021 | G68: новое | H68: /s/ eats, /ɪz/ watches, /z/ swims | I68: 7–9 | J68: =IFERROR(INDEX('Уроки'!$H:$H,MATCH(F68,'Уроки'!$A:$A,0)),"") | K68: =IFERROR(INDEX('Уроки'!$J:$J,MATCH(F68,'Уроки'!$A:$A,0)),"") | L68: Spotlight / 3 класс / Module 8 · Day by day / Present Simple / Present Simple: произношение окончания -s/-es (/s/, /z/, /ɪz/)
A69: 3 | B69: Module 8 · Day by day | D69: Present Simple | E69: Present Simple: значение — регулярные действия, распорядок дня, привычки | F69: Мл-022 | G69: повторение | H69: I get up at 8 every day | I69: 7–9 | J69: =IFERROR(INDEX('Уроки'!$H:$H,MATCH(F69,'Уроки'!$A:$A,0)),"") | K69: =IFERROR(INDEX('Уроки'!$J:$J,MATCH(F69,'Уроки'!$A:$A,0)),"") | L69: Spotlight / 3 класс / Module 8 · Day by day / Present Simple / Present Simple: значение — регулярные действия, распорядок дня, привычки
... A71: 3 | B71: Module 8 · Day by day | D71: Prepositions of time | E71: Prepositions of time: on — дни недели и праздничные дни | F71: Мл-097 | G71: новое | H71: on Monday | I71: 7–9 | J71: =IFERROR(INDEX('Уроки'!$H:$H,MATCH(F71,'Уроки'!$A:$A,0)),"") | K71: =IFERROR(INDEX('Уроки'!$J:$J,MATCH(F71,'Уроки'!$A:$A,0)),"") | L71: Spotlight / 3 класс / Module 8 · Day by day / Prepositions of time / Prepositions of time: on — дни недели и праздничные дни
A72: 3 | B72: Module 8 · Day by day | D72: Prepositions of time | E72: Prepositions of time: in — части суток (in the morning/afternoon/evening) | F72: Мл-098 | G72: новое | I72: 7–9 | J72: =IFERROR(INDEX('Уроки'!$H:$H,MATCH(F72,'Уроки'!$A:$A,0)),"") | K72: =IFERROR(INDEX('Уроки'!$J:$J,MATCH(F72,'Уроки'!$A:$A,0)),"") | L72: Spotlight / 3 класс / Module 8 · Day by day / Prepositions of time / Prepositions of time: in — части суток (in the morning/afternoon/evening)
A73: 4 | B73: Module 1 · Family and friends | D73: Present Continuous | E73: Present Continuous: утверждение (am/is/are + V-ing) | F73: Мл-011 | G73: повторение | I73: 7–9 | J73: =IFERROR(INDEX('Уроки'!$H:$H,MATCH(F73,'Уроки'!$A:$A,0)),"") | K73: =IFERROR(INDEX('Уроки'!$J:$J,MATCH(F73,'Уроки'!$A:$A,0)),"") | L73: Spotlight / 4 класс / Module 1 · Family and friends / Present Continuous / Present Continuous: утверждение (am/is/are + V-ing)
A74: 4 | B74: Module 1 · Family and friends | D74: Present Continuous | E74: Present Continuous: отрицание (I'm not / isn't / aren't) | F74: Мл-012 | G74: повторение | I74: 7–9 | J74: =IFERROR(INDEX('Уроки'!$H:$H,MATCH(F74,'Уроки'!$A:$A,0)),"") | K74: =IFERROR(INDEX('Уроки'!$J:$J,MATCH(F74,'Уроки'!$A:$A,0)),"") | L74: Spotlight / 4 класс / Module 1 · Family and friends / Present Continuous / Present Continuous: отрицание (I'm not / isn't / aren't)
A75: 4 | B75: Module 1 · Family and friends | D75: Present Continuous | E75: Present Continuous: общие вопросы (Am/Is/Are …?) | F75: Мл-013 | G75: повторение | I75: 7–9 | J75: =IFERROR(INDEX('Уроки'!$H:$H,MATCH(F75,'Уроки'!$A:$A,0)),"") | K75: =IFERROR(INDEX('Уроки'!$J:$J,MATCH(F75,'Уроки'!$A:$A,0)),"") | L75: Spotlight / 4 класс / Module 1 · Family and friends / Present Continuous / Present Continuous: общие вопросы (Am/Is/Are …?)
A76: 4 | B76: Module 1 · Family and friends | D76: Present Continuous | E76: Present Continuous: краткие ответы (Yes, I am / No, he isn't) | F76: Мл-014 | G76: повторение | I76: 7–9 | J76: =IFERROR(INDEX('Уроки'!$H:$H,MATCH(F76,'Уроки'!$A:$A,0)),"") | K76: =IFERROR(INDEX('Уроки'!$J:$J,MATCH(F76,'Уроки'!$A:$A,0)),"") | L76: Spotlight / 4 класс / Module 1 · Family and friends / Present Continuous / Present Continuous: краткие ответы (Yes, I am / No, he isn't)
A77: 4 | B77: Module 1 · Family and friends | D77: Present Continuous | E77: Present Continuous: значение — действие сейчас (now) | F77: Мл-015 | G77: повторение | H77: now, at the moment | I77: 7–9 | J77: =IFERROR(INDEX('Уроки'!$H:$H,MATCH(F77,'Уроки'!$A:$A,0)),"") | K77: =IFERROR(INDEX('Уроки'!$J:$J,MATCH(F77,'Уроки'!$A:$A,0)),"") | L77: Spotlight / 4 класс / Module 1 · Family and friends / Present Continuous / Present Continuous: значение — действие сейчас (now)
A78: 4 | B78: Module 1 · Family and friends | D78: Prepositions of place | E78: Prepositions of place: in, on, under | F78: Мл-093 | G78: повторение | I78: 7–9 | J78: =IFERROR(INDEX('Уроки'!$H:$H,MATCH(F78,'Уроки'!$A:$A,0)),"") | K78: =IFERROR(INDEX('Уроки'!$J:$J,MATCH(F78,'Уроки'!$A:$A,0)),"") | L78: Spotlight / 4 класс / Module 1 · Family and friends / Prepositions of place / Prepositions of place: in, on, under
A79: 4 | B79: Module 1 · Family and friends | D79: Prepositions of place | E79: Prepositions of place: next to, in front of, behind | F79: Мл-094 | G79: повторение | I79: 7–9 | J79: =IFERROR(INDEX('Уроки'!$H:$H,MATCH(F79,'Уроки'!$A:$A,0)),"") | K79: =IFERROR(INDEX('Уроки'!$J:$J,MATCH(F79,'Уроки'!$A:$A,0)),"") | L79: Spotlight / 4 класс / Module 1 · Family and friends / Prepositions of place / Prepositions of place: next to, in front of, behind
A80: 4 | B80: Module 1 · Family and friends | D80: Prepositions of place | E80: Prepositions of place: opposite, between | F80: Мл-095 | G80: новое | H80: новые в 4 кл. | I80: 7–9 | J80: =IFERROR(INDEX('Уроки'!$H:$H,MATCH(F80,'Уроки'!$A:$A,0)),"") | K80: =IFERROR(INDEX('Уроки'!$J:$J,MATCH(F80,'Уроки'!$A:$A,0)),"") | L80: Spotlight / 4 класс / Module 1 · Family and friends / Prepositions of place / Prepositions of place: opposite, between
A81: 4 | B81: Module 2 · A working day | D81: Present Simple | E81: Present Simple: утверждение (I/you/we/they V, he/she/it V-s) | F81: Мл-016 | G81: повторение | H81: все лица | I81: 7–9 | J81: =IFERROR(INDEX('Уроки'!$H:$H,MATCH(F81,'Уроки'!$A:$A,0)),"") | K81: =IFERROR(INDEX('Уроки'!$J:$J,MATCH(F81,'Уроки'!$A:$A,0)),"") | L81: Spotlight / 4 класс / Module 2 · A working day / Present Simple / Present Simple: утверждение (I/you/we/they V, he/she/it V-s)
A82: 4 | B82: Module 2 · A working day | D82: Present Simple | E82: Present Simple: отрицание (don't/doesn't) | F82: Мл-017 | G82: повторение | H82: все лица | I82: 7–9 | J82: =IFERROR(INDEX('Уроки'!$H:$H,MATCH(F82,'Уроки'!$A:$A,0)),"") | K82: =IFERROR(INDEX('Уроки'!$J:$J,MATCH(F82,'Уроки'!$A:$A,0)),"") | L82: Spotlight / 4 класс / Module 2 · A working day / Present Simple / Present Simple: отрицание (don't/doesn't)
A83: 4 | B83: Module 2 · A working day | D83: Present Simple | E83: Present Simple: общие вопросы (Do/Does …?) | F83: Мл-018 | G83: повторение | H83: все лица | I83: 7–9 | J83: =IFERROR(INDEX('Уроки'!$H:$H,MATCH(F83,'Уроки'!$A:$A,0)),"") | K83: =IFERROR(INDEX('Уроки'!$J:$J,MATCH(F83,'Уроки'!$A:$A,0)),"") | L83: Spotlight / 4 класс / Module 2 · A working day / Present Simple / Present Simple: общие вопросы (Do/Does …?)
A84: 4 | B84: Module 2 · A working day | D84: Present Simple | E84: Present Simple: краткие ответы (Yes, I do / No, he doesn't) | F84: Мл-019 | G84: повторение | H84: все лица | I84: 7–9 | J84: =IFERROR(INDEX('Уроки'!$H:$H,MATCH(F84,'Уроки'!$A:$A,0)),"") | K84: =IFERROR(INDEX('Уроки'!$J:$J,MATCH(F84,'Уроки'!$A:$A,0)),"") | L84: Spotlight / 4 класс / Module 2 · A working day / Present Simple / Present Simple: краткие ответы (Yes, I do / No, he doesn't)
A85: 4 | B85: Module 2 · A working day | D85: Present Simple | E85: Present Simple: орфография окончания -s/-es (3 л. ед. ч.) | F85: Мл-020 | G85: повторение | I85: 7–9 | J85: =IFERROR(INDEX('Уроки'!$H:$H,MATCH(F85,'Уроки'!$A:$A,0)),"") | K85: =IFERROR(INDEX('Уроки'!$J:$J,MATCH(F85,'Уроки'!$A:$A,0)),"") | L85: Spotlight / 4 класс / Module 2 · A working day / Present Simple / Present Simple: орфография окончания -s/-es (3 л. ед. ч.)
A86: 4 | B86: Module 2 · A working day | D86: Present Simple | E86: Present Simple: произношение окончания -s/-es (/s/, /z/, /ɪz/) | F86: Мл-021 | G86: повторение | I86: 7–9 | J86: =IFERROR(INDEX('Уроки'!$H:$H,MATCH(F86,'Уроки'!$A:$A,0)),"") | K86: =IFERROR(INDEX('Уроки'!$J:$J,MATCH(F86,'Уроки'!$A:$A,0)),"") | L86: Spotlight / 4 класс / Module 2 · A working day / Present Simple / Present Simple: произношение окончания -s/-es (/s/, /z/, /ɪz/)
A87: 4 | B87: Module 2 · A working day | D87: Present Simple | E87: Present Simple: значение — регулярные действия, распорядок дня, привычки | F87: Мл-022 | G87: расширение | H87: сигнальные слова: every day/week…, in the morning, on Monday, once/twice a week | I87: 7–9 | J87: =IFERROR(INDEX('Уроки'!$H:$H,MATCH(F87,'Уроки'!$A:$A,0)),"") | K87: =IFERROR(INDEX('Уроки'!$J:$J,MATCH(F87,'Уроки'!$A:$A,0)),"") | L87: Spotlight / 4 класс / Module 2 · A working day / Present Simple / Present Simple: значение — регулярные действия, распорядок дня, привычки
A88: 4 | B88: Module 2 · A working day | D88: have to | E88: have to: значение — необходимость из-за обстоятельств (утверждение) | F88: Мл-050 | G88: новое | H88: I have to be at school at 9 | I88: 7–9 | J88: =IFERROR(INDEX('Уроки'!$H:$H,MATCH(F88,'Уроки'!$A:$A,0)),"") | K88: =IFERROR(INDEX('Уроки'!$J:$J,MATCH(F88,'Уроки'!$A:$A,0)),"") | L88: Spotlight / 4 класс / Module 2 · A working day / have to / have to: значение — необходимость из-за обстоятельств (утверждение)
A89: 4 | B89: Module 2 · A working day | D89: have to | E89: have to: don't / doesn't have to — отсутствие необходимости | F89: Мл-051 | G89: новое | H89: don't / doesn't have to | I89: 7–9 | J89: =IFERROR(INDEX('Уроки'!$H:$H,MATCH(F89,'Уроки'!$A:$A,0)),"") | K89: =IFERROR(INDEX('Уроки'!$J:$J,MATCH(F89,'Уроки'!$A:$A,0)),"") | L89: Spotlight / 4 класс / Module 2 · A working day / have to / have to: don't / doesn't have to — отсутствие необходимости
A90: 4 | B90: Module 2 · A working day | D90: have to | E90: have to: вопросы и краткие ответы — Do you have to…? | F90: Мл-052 | G90: новое | H90: Do you have to…? — Yes, I do | I90: 7–9 | J90: =IFERROR(INDEX('Уроки'!$H:$H,MATCH(F90,'Уроки'!$A:$A,0)),"") | K90: =IFERROR(INDEX('Уроки'!$J:$J,MATCH(F90,'Уроки'!$A:$A,0)),"") | L90: Spotlight / 4 класс / Module 2 · A working day / have to / have to: вопросы и краткие ответы — Do you have to…?
A91: 4 | B91: Module 2 · A working day | D91: Adverbs of frequency | E91: Adverbs of frequency: значение — never, sometimes, usually, often, always | F91: Мл-081 | G91: новое | H91: never, sometimes, usually, often, always; с Present Simple | I91: 7–9 | J91: =IFERROR(INDEX('Уроки'!$H:$H,MATCH(F91,'Уроки'!$A:$A,0)),"") | K91: =IFERROR(INDEX('Уроки'!$J:$J,MATCH(F91,'Уроки'!$A:$A,0)),"") | L91: Spotlight / 4 класс / Module 2 · A working day / Adverbs of frequency / Adverbs of frequency: значение — never, sometimes, usually, often, always
A92: 4 | B92: Module 2 · A working day | D92: Adverbs of frequency | E92: Adverbs of frequency: место — перед смысловым глаголом, после be | F92: Мл-082 | G92: новое | H92: только примерами: перед смысловым глаголом и после is; правило не сформулировано | I92: 7–9 | J92: =IFERROR(INDEX('Уроки'!$H:$H,MATCH(F92,'Уроки'!$A:$A,0)),"") | K92: =IFERROR(INDEX('Уроки'!$J:$J,MATCH(F92,'Уроки'!$A:$A,0)),"") | L92: Spotlight / 4 класс / Module 2 · A working day / Adverbs of frequency / Adverbs of frequency: место — перед смысловым глаголом, после be
A93: 4 | B93: Module 3 · Tasty treats | D93: may/might | E93: may/might: may — спросить разрешения (May I…?) и ответы | F93: Мл-053 | G93: новое | H93: официально; Certainly./Of course you may. / No, you may not. | I93: 7–9 | J93: =IFERROR(INDEX('Уроки'!$H:$H,MATCH(F93,'Уроки'!$A:$A,0)),"") | K93: =IFERROR(INDEX('Уроки'!$J:$J,MATCH(F93,'Уроки'!$A:$A,0)),"") | L93: Spotlight / 4 класс / Module 3 · Tasty treats / may/might / may/might: may — спросить разрешения (May I…?) и ответы
A94: 4 | B94: Module 3 · Tasty treats | D94: Countable / Uncountable nouns | E94: Countable / Uncountable: различие исчисляемых и неисчисляемых | F94: Мл-056 | G94: повторение | H94: только в рамках much/many и how much/how many | I94: 7–9 | J94: =IFERROR(INDEX('Уроки'!$H:$H,MATCH(F94,'Уроки'!$A:$A,0)),"") | K94: =IFERROR(INDEX('Уроки'!$J:$J,MATCH(F94,'Уроки'!$A:$A,0)),"") | L94: Spotlight / 4 класс / Module 3 · Tasty treats / Countable / Uncountable nouns / Countable / Uncountable: различие исчисляемых и неисчисляемых
A95: 4 | B95: Module 3 · Tasty treats | D95: much/many/a lot of | E95: much/many/a lot of: a lot of / lots of — в утверждениях (исчисляемые и неисчисляемые) | F95: Мл-071 | G95: новое | H95: She's got a lot of friends. There is a lot of cheese | I95: 7–9 | J95: =IFERROR(INDEX('Уроки'!$H:$H,MATCH(F95,'Уроки'!$A:$A,0)),"") | K95: =IFERROR(INDEX('Уроки'!$J:$J,MATCH(F95,'Уроки'!$A:$A,0)),"") | L95: Spotlight / 4 класс / Module 3 · Tasty treats / much/many/a lot of / much/many/a lot of: a lot of / lots of — в утверждениях (исчисляемые и неисчисляемые)
A96: 4 | B96: Module 3 · Tasty treats | D96: much/many/a lot of | E96: much/many/a lot of: much/many — отрицание | F96: Мл-072 | G96: новое | H96: There isn't much butter / aren't many apples | I96: 7–9 | J96: =IFERROR(INDEX('Уроки'!$H:$H,MATCH(F96,'Уроки'!$A:$A,0)),"") | K96: =IFERROR(INDEX('Уроки'!$J:$J,MATCH(F96,'Уроки'!$A:$A,0)),"") | L96: Spotlight / 4 класс / Module 3 · Tasty treats / much/many/a lot of / much/many/a lot of: much/many — отрицание
A97: 4 | B97: Module 3 · Tasty treats | D97: much/many/a lot of | E97: much/many/a lot of: much/many — вопросы | F97: Мл-073 | G97: новое | H97: Is there much sugar? Are there many girls? | I97: 7–9 | J97: =IFERROR(INDEX('Уроки'!$H:$H,MATCH(F97,'Уроки'!$A:$A,0)),"") | K97: =IFERROR(INDEX('Уроки'!$J:$J,MATCH(F97,'Уроки'!$A:$A,0)),"") | L97: Spotlight / 4 класс / Module 3 · Tasty treats / much/many/a lot of / much/many/a lot of: much/many — вопросы
A98: 4 | B98: Module 3 · Tasty treats | D98: much/many/a lot of | E98: much/many/a lot of: How much? / How many? | F98: Мл-074 | G98: новое | I98: 7–9 | J98: =IFERROR(INDEX('Уроки'!$H:$H,MATCH(F98,'Уроки'!$A:$A,0)),"") | K98: =IFERROR(INDEX('Уроки'!$J:$J,MATCH(F98,'Уроки'!$A:$A,0)),"") | L98: Spotlight / 4 класс / Module 3 · Tasty treats / much/many/a lot of / much/many/a lot of: How much? / How many?
A99: 4 | B99: Module 3 · Tasty treats | D99: much/many/a lot of | E99: much/many/a lot of: краткие ответы и a lot / lots без существительного | F99: Мл-075 | G99: новое | H99: Not much. / Not many. / A lot. | I99: 7–9 | J99: =IFERROR(INDEX('Уроки'!$H:$H,MATCH(F99,'Уроки'!$A:$A,0)),"") | K99: =IFERROR(INDEX('Уроки'!$J:$J,MATCH(F99,'Уроки'!$A:$A,0)),"") | L99: Spotlight / 4 класс / Module 3 · Tasty treats / much/many/a lot of / much/many/a lot of: краткие ответы и a lot / lots без существительного
A100: 4 | B100: Module 3 · Tasty treats | D100: Question words | E100: Question words: How much? / How many? | F100: Мл-100 | G100: новое | H100: How much — неисчисляемые, How many — исчисляемые; в разделе Much/Many/A lot of | I100: 7–9 | J100: =IFERROR(INDEX('Уроки'!$H:$H,MATCH(F100,'Уроки'!$A:$A,0)),"") | K100: =IFERROR(INDEX('Уроки'!$J:$J,MATCH(F100,'Уроки'!$A:$A,0)),"") | L100: Spotlight / 4 класс / Module 3 · Tasty treats / Question words / Question words: How much? / How many?
A101: 4 | B101: Module 4 · At the zoo! | D101: Present Simple vs Present Continuous | E101: Present Simple vs Present Continuous: привычка vs сейчас | F101: Мл-029 | G101: новое | H101: регулярные действия vs момент речи | I101: 7–9 | J101: =IFERROR(INDEX('Уроки'!$H:$H,MATCH(F101,'Уроки'!$A:$A,0)),"") | K101: =IFERROR(INDEX('Уроки'!$J:$J,MATCH(F101,'Уроки'!$A:$A,0)),"") | L101: Spotlight / 4 класс / Module 4 · At the zoo! / Present Simple vs Present Continuous / Present Simple vs Present Continuous: привычка vs сейчас
A102: 4 | B102: Module 4 · At the zoo! | D102: must/mustn't | E102: must/mustn't: must — обязанность, необходимость | F102: Мл-054 | G102: новое | H102: I must put my rubbish in the bin | I102: 7–9 | J102: =IFERROR(INDEX('Уроки'!$H:$H,MATCH(F102,'Уроки'!$A:$A,0)),"") | K102: =IFERROR(INDEX('Уроки'!$J:$J,MATCH(F102,'Уроки'!$A:$A,0)),"") | L102: Spotlight / 4 класс / Module 4 · At the zoo! / must/mustn't / must/mustn't: must — обязанность, необходимость
A103: 4 | B103: Module 4 · At the zoo! | D103: must/mustn't | E103: must/mustn't: mustn't — запрет | F103: Мл-055 | G103: новое | H103: must not (mustn't — только в заголовке); вопросов нет | I103: 7–9 | J103: =IFERROR(INDEX('Уроки'!$H:$H,MATCH(F103,'Уроки'!$A:$A,0)),"") | K103: =IFERROR(INDEX('Уроки'!$J:$J,MATCH(F103,'Уроки'!$A:$A,0)),"") | L103: Spotlight / 4 класс / Module 4 · At the zoo! / must/mustn't / must/mustn't: mustn't — запрет
A104: 4 | B104: Module 4 · At the zoo! | D104: Comparatives & Superlatives | E104: Comparatives & Superlatives: сравнительная степень — -er + than | F104: Мл-083 | G104: новое | H104: small — smaller; + than при сравнении | I104: 7–9 | J104: =IFERROR(INDEX('Уроки'!$H:$H,MATCH(F104,'Уроки'!$A:$A,0)),"") | K104: =IFERROR(INDEX('Уроки'!$J:$J,MATCH(F104,'Уроки'!$A:$A,0)),"") | L104: Spotlight / 4 класс / Module 4 · At the zoo! / Comparatives & Superlatives / Comparatives & Superlatives: сравнительная степень — -er + than
A105: 4 | B105: Module 4 · At the zoo! | D105: Comparatives & Superlatives | E105: Comparatives & Superlatives: сравнительная степень — more (многосложные) | F105: Мл-084 | G105: новое | H105: beautiful — more beautiful | I105: 7–9 | J105: =IFERROR(INDEX('Уроки'!$H:$H,MATCH(F105,'Уроки'!$A:$A,0)),"") | K105: =IFERROR(INDEX('Уроки'!$J:$J,MATCH(F105,'Уроки'!$A:$A,0)),"") | L105: Spotlight / 4 класс / Module 4 · At the zoo! / Comparatives & Superlatives / Comparatives & Superlatives: сравнительная степень — more (многосложные)
A106: 4 | B106: Module 4 · At the zoo! | D106: Comparatives & Superlatives | E106: Comparatives & Superlatives: орфография -er/-est (удвоение, -e, y → i) | F106: Мл-085 | G106: новое | H106: nice — nicer, thin — thinner, funny — funnier; только для -er | I106: 7–9 | J106: =IFERROR(INDEX('Уроки'!$H:$H,MATCH(F106,'Уроки'!$A:$A,0)),"") | K106: =IFERROR(INDEX('Уроки'!$J:$J,MATCH(F106,'Уроки'!$A:$A,0)),"") | L106: Spotlight / 4 класс / Module 4 · At the zoo! / Comparatives & Superlatives / Comparatives & Superlatives: орфография -er/-est (удвоение, -e, y → i)
A107: 4 | B107: Module 4 · At the zoo! | D107: Comparatives & Superlatives | E107: Comparatives & Superlatives: двусложные на -y/-er/-ow — -er/-est | F107: Мл-089 | G107: новое | H107: только на -y: busy — busier | I107: 7–9 | J107: =IFERROR(INDEX('Уроки'!$H:$H,MATCH(F107,'Уроки'!$A:$A,0)),"") | K107: =IFERROR(INDEX('Уроки'!$J:$J,MATCH(F107,'Уроки'!$A:$A,0)),"") | L107: Spotlight / 4 класс / Module 4 · At the zoo! / Comparatives & Superlatives / Comparatives & Superlatives: двусложные на -y/-er/-ow — -er/-est
A108: 4 | B108: Module 5 · Where were you yesterday? | D108: to be (Past: was/were) | E108: to be (Past): утверждение — was / were | F108: Мл-043 | G108: повторение | I108: 7–9 | J108: =IFERROR(INDEX('Уроки'!$H:$H,MATCH(F108,'Уроки'!$A:$A,0)),"") | K108: =IFERROR(INDEX('Уроки'!$J:$J,MATCH(F108,'Уроки'!$A:$A,0)),"") | L108: Spotlight / 4 класс / Module 5 · Where were you yesterday? / to be (Past: was/were) / to be (Past): утверждение — was / were
A109: 4 | B109: Module 5 · Where were you yesterday? | D109: to be (Past: was/were) | E109: to be (Past): отрицание — wasn't / weren't | F109: Мл-044 | G109: повторение | I109: 7–9 | J109: =IFERROR(INDEX('Уроки'!$H:$H,MATCH(F109,'Уроки'!$A:$A,0)),"") | K109: =IFERROR(INDEX('Уроки'!$J:$J,MATCH(F109,'Уроки'!$A:$A,0)),"") | L109: Spotlight / 4 класс / Module 5 · Where were you yesterday? / to be (Past: was/were) / to be (Past): отрицание — wasn't / weren't
A110: 4 | B110: Module 5 · Where were you yesterday? | D110: to be (Past: was/were) | E110: to be (Past): вопросы и краткие ответы | F110: Мл-045 | G110: повторение | I110: 7–9 | J110: =IFERROR(INDEX('Уроки'!$H:$H,MATCH(F110,'Уроки'!$A:$A,0)),"") | K110: =IFERROR(INDEX('Уроки'!$J:$J,MATCH(F110,'Уроки'!$A:$A,0)),"") | L110: Spotlight / 4 класс / Module 5 · Where were you yesterday? / to be (Past: was/were) / to be (Past): вопросы и краткие ответы
A111: 4 | B111: Module 5 · Where were you yesterday? | D111: to be (Past: was/were) | E111: to be (Past): слова-указатели прошедшего времени | F111: Мл-046 | G111: повторение | H111: yesterday, last…, …ago, in 1975 | I111: 7–9 | J111: =IFERROR(INDEX('Уроки'!$H:$H,MATCH(F111,'Уроки'!$A:$A,0)),"") | K111: =IFERROR(INDEX('Уроки'!$J:$J,MATCH(F111,'Уроки'!$A:$A,0)),"") | L111: Spotlight / 4 класс / Module 5 · Where were you yesterday? / to be (Past: was/were) / to be (Past): слова-указатели прошедшего времени
A112: 4 | B112: Module 5 · Where were you yesterday? | D112: Ordinal numbers | E112: Ordinal numbers: first, second, third и составные (21st, 22nd) | F112: Мл-090 | G112: новое | H112: 1–31 с сокращениями 1st, 2nd, 3rd | I112: 7–9 | J112: =IFERROR(INDEX('Уроки'!$H:$H,MATCH(F112,'Уроки'!$A:$A,0)),"") | K112: =IFERROR(INDEX('Уроки'!$J:$J,MATCH(F112,'Уроки'!$A:$A,0)),"") | L112: Spotlight / 4 класс / Module 5 · Where were you yesterday? / Ordinal numbers / Ordinal numbers: first, second, third и составные (21st, 22nd)
A113: 4 | B113: Module 5 · Where were you yesterday? | D113: Ordinal numbers | E113: Ordinal numbers: образование с -th и орфография (fifth, ninth, twelfth, twentieth) | F113: Мл-091 | G113: новое | H113: список до thirty-first | I113: 7–9 | J113: =IFERROR(INDEX('Уроки'!$H:$H,MATCH(F113,'Уроки'!$A:$A,0)),"") | K113: =IFERROR(INDEX('Уроки'!$J:$J,MATCH(F113,'Уроки'!$A:$A,0)),"") | L113: Spotlight / 4 класс / Module 5 · Where were you yesterday? / Ordinal numbers / Ordinal numbers: образование с -th и орфография (fifth, ninth, twelfth, twentieth)
A114: 4 | B114: Module 5 · Where were you yesterday? | D114: Ordinal numbers | E114: Ordinal numbers: с артиклем the и даты | F114: Мл-092 | G114: новое | H114: fifteen — the fifteenth; даты | I114: 7–9 | J114: =IFERROR(INDEX('Уроки'!$H:$H,MATCH(F114,'Уроки'!$A:$A,0)),"") | K114: =IFERROR(INDEX('Уроки'!$J:$J,MATCH(F114,'Уроки'!$A:$A,0)),"") | L114: Spotlight / 4 класс / Module 5 · Where were you yesterday? / Ordinal numbers / Ordinal numbers: с артиклем the и даты
...

Sheet Пересечения
A1: № | B1: Что повторяется | C1: Где встречается (тема: подтема — классы) | D1: Где живёт урок (предложение) | E1: Что делать в остальных местах | F1: Решение методиста
A2: 1 | B2: a few / a little | C2: • a few/a little — 6 подтем, 5–11 кл. • Quantifiers: a few/few vs a little/little — 8 кл. | D2: a few/a little | E2: Quantifiers 8 кл. — ссылка на уроки a few/a little, своего урока не делать.
A3: 2 | B3: much / many / a lot of | C3: • much/many/a lot of — 5 подтем, 4–11 кл. • Quantifiers: a lot of / lots of; much/many — отрицания и вопросы — 8 кл. | D3: much/many/a lot of | E3: Quantifiers 8 кл. — ссылка.
A4: 3 | B4: every / each | C4: • Determiners (every/each) — 4 подтемы, 9–10 кл. • Quantifiers: every vs each — 11 кл. • Indefinite pronouns: every + ед. ч.; everybody, everything — 9, 11 кл. | D4: Determiners (every/each) | E4: Quantifiers 11 кл. — ссылка. В Indefinite pronouns оставить только производные everybody/everything/everywhere.
A5: 4 | B5: hardly any | C5: • Indefinite pronouns: hardly any — 9, 11 кл. • Quantifiers: hardly any — 11 кл. | D5: Indefinite pronouns | E5: Quantifiers — ссылка. У Quantifiers остаются свои уроки: a couple of / several; a great deal of / plenty of.
A6: 5 | B6: a bottle of, a packet of… (количество неисчисляемых) | C6: • Partitives — 2 подтемы, 7 кл. • Countable / Uncountable: количество с неисчисляемыми (a jar of, a bottle of) — 5, 6, 11 кл. | D6: Partitives (a bottle of…) | E6: Подтема в Countable / Uncountable — ссылка на урок Partitives (обе в группе 10+, урок один).
A7: 6 | B7: Существительные только во мн. ч. (jeans, scissors, clothes) | C7: • Plurals (irregular): только во мн. ч. — 5 кл. • Countable / Uncountable: существительные без ед. числа — 5 кл. • Plurals (only plural / collective nouns): только мн. ч. — 8 кл. | D7: Plurals (only plural / collective nouns) | E7: В 5 кл. обе подтемы — ссылка на этот урок.
A8: 7 | B8: Собирательные существительные (family, team, police) | C8: • Plurals (only plural / collective nouns): собирательные — 8 кл. • Countable / Uncountable: собирательные и составные — 11 кл. | D8: Plurals (only plural / collective nouns) | E8: Countable 11 кл. — ссылка; составные (homework, countryside) оставить в Countable.
A9: 8 | B9: some / any с существительными | C9: • a/an/some/any — 6 подтем, 3–7 кл. • Indefinite pronouns: some/any/no + неисчисляемые и мн. ч.; some в просьбах; any в вопросах и отрицаниях — 9–11 кл. | D9: a/an/some/any (some/any + существительное) | E9: В Indefinite pronouns оставить то, чего нет в a/an/some/any: производные (somebody, anything, nowhere), no- вместо not any, any = «любой», глагол в ед. ч. Остальное — ссылка. У 3 кл. (7–9 лет) урок свой в любом случае.
A10: 9 | B10: There is / There are | C10: • There is / There are — 3, 5 кл. • Countable / Uncountable: There is/are + исчисляемые/неисчисляемые (утв., отр., вопрос) — 7 кл. | D10: There is / There are | E10: Countable 7 кл. — ссылка (для 10+ урок There is/are уже есть с 5 кл.).
A11: 10 | B11: Запрет: mustn't / can't | C11: • must/mustn't: mustn't — запрет (4–10 кл.); can't как запрет (6, 8, 10 кл.) • can (permission/request): can't — запрет (5, 6, 9, 10, 11 кл.) | D11: must/mustn't — один урок «Запрет: mustn't и can't» | E11: can (permission/request) — ссылка; в нём остаются Can I…? / Can you…? / can vs may.
A12: 11 | B12: Обязанность: must vs have to, had to | C12: • must/mustn't: must только в настоящем, в других временах have to / had to — 7–9 кл. • have to: had to, didn't have to — 7–10 кл. • must/have to (obligation): must vs have to; had to; should/ought to — долг — 11 кл. • should/shouldn't: обязательство, долг — 8–10 кл. | D12: must/have to (obligation) — урок-сравнение «must vs have to» | E12: had to / didn't have to — урок в have to; «долг» should/ought to — урок в should. Подтема в must/mustn't и в must/have to 11 кл. — ссылки.
A13: 12 | B13: Совет: should / ought to / shall / had better | C13: • should/shouldn't: совет; ought to; Shall I…? — совет; had better — 7–11 кл. • Modal verbs (functions): совет (should / ought to / shall) — 8, 9 кл. • Semi-modals: had better (= should) — 11 кл. | D13: should/shouldn't | E13: Modal verbs (functions) и Semi-modals — ссылки.
... A24: 23 | B24: Reported questions и Indirect questions | C24: • Reported questions — 5 подтем, 8–11 кл. • Indirect questions — 3 подтемы, 8–11 кл. | D24: это НЕ дубль | E24: Reported questions — пересказ чужого вопроса со сдвигом времён; Indirect questions — вежливый вопрос (Could you tell me…?) без сдвига. Оба урока нужны; в каждом полезно показать разницу.

Sheet Кандидаты в вебинары
A1: Группа | B1: Тема | C1: С какого класса | D1: Подтем без ничего (красные) | E1: из них новое в учебнике | F1: Красные подтемы | G1: Остальные подтемы темы
A2: 7–9 | B2: Prepositions of place | C2: 3 кл. | D2: 1 | E2: 1 | F2: • opposite, between | G2: с видео: 2
A3: 7–9 | B3: Present Simple | C3: 3 кл. | D3: 1 | E3: 1 | F3: • произношение окончания -s/-es (/s/, /z/, /ɪz/) | G3: с видео: 3, вебинар в расписании: 3
A4: 7–9 | B4: There is / There are | C4: 3 кл. | D4: 1 | E4: 1 | F4: • вопросы — Is there…? / Are there…? | G4: с видео: 3
A5: 7–9 | B5: a/an | C5: 3 кл. | D5: 1 | E5: 1 | F5: • неопределённый артикль — только с исчисляемыми в ед. ч. | G5: с видео: 1
A6: 7–9 | B6: Comparatives & Superlatives | C6: 4 кл. | D6: 2 | E6: 2 | F6: • превосходная степень — the most • двусложные на -y/-er/-ow — -er/-est | G6: с видео: 4, вебинар в расписании: 1
A7: 7–9 | B7: Ordinal numbers | C7: 4 кл. | D7: 1 | E7: 1 | F7: • с артиклем the и даты | G7: с видео: 2
A8: 7–9 | B8: have to | C8: 4 кл. | D8: 1 | E8: 1 | F8: • вопросы и краткие ответы — Do you have to…? | G8: с видео: 2
A9: 10+ | B9: Word formation | C9: 5 кл. | D9: 22 | E9: 22 | F9: • -able, -ous, -ing • -al • -er, -or, -man, -ist, -ic • -ly • -tion, -sion • conversion (a dress – to dress) • nationalities -an/-ish/-ian/-ese • un- • -ion, -tion, -ance • -ise, -ize • -ness, -ment • il-, im-, in-, ir- • negative adjectives • abstract nouns • nouns from adjectives • participle adjectives -ed/-ing • revision • verbs from nouns/adjectives • verbs with prefixes • forming verbs • personal nouns • prefixes | G9: с видео: 6
A10: 10+ | B10: Present Simple | C10: 5 кл. | D10: 10 | E10: 5 | F10: • утверждение (I/you/we/they V, he/she/it V-s) • отрицание (don't/doesn't) • общие вопросы (Do/Does …?) • краткие ответы (Yes, I do / No, he doesn't) • орфография окончания -s/-es (3 л. ед. ч.) • значение — непреложные истины и законы природы • значение — чувства и эмоции • значение — обзоры, спортивные комментарии, повествование • значение — восклицания (Here comes …!) • значение — последовательные действия в настоящем | G10: с видео: 3
A11: 10+ | B11: Prepositions of place | C11: 5 кл. | D11: 8 | E11: 5 | F11: • in, on, under • next to, in front of, behind • opposite, between • near, beside • at — at school/work/home, в адресах • in — устойчивые выражения (in bed, in hospital, in the sky, in a picture) • in — города, страны, континенты • on — on the left/right, on the first floor
A12: 10+ | B12: Past Simple | C12: 5 кл. | D12: 7 | E12: 2 | F12: • правильные глаголы — отрицание (didn't + V) • правильные глаголы — вопросы (Did …?) • краткие ответы (Yes, I did / No, I didn't) • неправильные глаголы — отрицание (didn't go) • неправильные глаголы — вопросы (Did … go?) • значение — повторяющиеся действия и привычки в прошлом • значение — завершённые действия без связи с настоящим | G12: с видео: 6, вебинар в расписании: 1
A13: 10+ | B13: Present Continuous | C13: 5 кл. | D13: 7 | E13: 3 | F13: • утверждение (am/is/are + V-ing) • отрицание (I'm not / isn't / aren't) • общие вопросы (Am/Is/Are …?) • краткие ответы (Yes, I am / No, he isn't) • орфография -ing • значение — меняющиеся и развивающиеся ситуации • значение — always + раздражение | G13: с видео: 4
A14: 10+ | B14: Articles (a/an/the/zero) | C14: 5 кл. | D14: 6 | E14: 6 | F14: • нулевой артикль — при другом определителе (my, this, some, числительное, 's) • a/an = per; деньги, дроби, меры, частота, скорость • a/an с болезнями (a cold, но flu) • a/the + ед. ч. — обобщение группы • the и нулевой — театры, отели, музеи, газеты; названия с именем (Victoria Station, Harrods) • the — люди: фамилии, титулы, the + прилагательное (the rich) | G14: с видео: 6, вебинар в расписании: 1
A15: 10+ | B15: Plurals (regular) | C15: 5 кл. | D15: 6 | E15: 2 | F15: • основное правило — + -s • орфография — + -es после -s, -ss, -sh, -ch, -x, -o • орфография — -y → -ies (но гласная + y → -s) • орфография — -f/-fe → -ves • исключения на -o — только -s (photos, videos) • произношение окончания -(e)s
A16: 10+ | B16: Prepositions of time | C16: 5 кл. | D16: 6 | E16: 3 | F16: • at — время, праздники, at night/at noon/at the weekend • on — дни недели и праздничные дни • on — даты, день недели + часть дня, on a hot day • in — части суток (in the morning/afternoon/evening) • in — месяцы, времена года, годы, века • in = «через» (in an hour, in a week)
A17: 10+ | B17: have got | C17: 5 кл. | D17: 6 | E17: 1 | F17: • утверждение — have got / has got (полные и краткие формы) • отрицание — haven't got / hasn't got • вопросы и краткие ответы • значение — принадлежность (иметь) • значение — описание внешности людей, животных, предметов • значение — родственные отношения
A18: 10+ | B18: Comparatives & Superlatives | C18: 5 кл. | D18: 5 | E18: 2 | F18: • орфография -er/-est (удвоение, -e, y → i) • неправильные прилагательные (good, bad, many/much, little) • двусложные на -y/-er/-ow — -er/-est • прилагательные с двумя способами (clever, quiet, friendly…) • far — farther/further, old — elder/eldest | G18: с видео: 7
A19: 10+ | B19: There is / There are | C19: 5 кл. | D19: 5 | E19: 1 | F19: • there is — утверждение (ед. ч.) • there are — утверждение (мн. ч.) • отрицание — there isn't / there aren't • вопросы — Is there…? / Are there…? • some / any в конструкции
A20: 10+ | B20: Countable / Uncountable nouns | C20: 5 кл. | D20: 4 | E20: 4 | F20: • исключения с a/an (a help, a pity, a shame) • группы неисчисляемых — предметы, языки, игры, болезни, явления природы • «ловушки» — advice, information, news, furniture, luggage, money • длительность, расстояние, деньги как целое — глагол в ед. ч. | G20: с видео: 9
A21: 10+ | B21: can (permission/request) | C21: 5 кл. | D21: 4 | E21: 4 | F21: • просьба — Can you…? / Can I have…? • предложение помощи — Can I…? • can vs may — разрешение (may формальнее) • предложения (offers/suggestions) — can, could, would, shall | G21: с видео: 2
A22: 10+ | B22: must/mustn't | C22: 5 кл. | D22: 4 | E22: 4 | F22: • can't как запрет (= mustn't) • must — настойчивый совет • must только в настоящем; в других временах — have to / had to • must — логический вывод | G22: с видео: 2
A23: 10+ | B23: Imperative | C23: 5 кл. | D23: 3 | E23: 3 | F23: • значение — инструкция, указание • значение — предложение (Have some cake) • значение — просьба, вежливость с please | G23: с видео: 3
A24: 10+ | B24: Personal pronouns (subject) | C24: 5 кл. | D24: 3 | E24: 3 | F24: • формы I, you, he, she, it, we, you, they • употребление — подлежащее вместо существительного • he/she vs it vs they — выбор местоимения
A25: 10+ | B25: Present Simple vs Present Continuous | C25: 5 кл. | D25: 3 | E25: 3 | F25: • постоянное состояние vs временная ситуация • повторяющиеся действия vs настоящий период (these days) • будущее — расписание vs договорённость | G25: с видео: 1
A26: 10+ | B26: a/an/some/any | C26: 5 кл. | D26: 3 | E26: 2 | F26: • some в вопросах — просьба и предложение • a/an vs some/any — исчисляемые ед. ч. во всех типах предложений • перевод some — «несколько» / «немного» / не переводится | G26: с видео: 3
A27: 10+ | B27: can (ability) | C27: 5 кл. | D27: 3 | E27: 0 | F27: • значение — умение; утверждение can + глагол без to • отрицание — cannot / can't • вопросы и краткие ответы
A28: 10+ | B28: to be (Past: was/were) | C28: 5 кл. | D28: 3 | E28: 0 | F28: • утверждение — was / were • отрицание — wasn't / weren't • вопросы и краткие ответы
A29: 10+ | B29: to be (Present) | C29: 5 кл. | D29: 3 | E29: 0 | F29: • утверждение — am/is/are, полные и краткие формы • отрицание — am not / isn't / aren't • вопросы и краткие ответы
A30: 10+ | B30: Adverbs of frequency | C30: 5 кл. | D30: 2 | E30: 2 | F30: • место — после вспомогательных и модальных глаголов • seldom / rarely | G30: с видео: 3
A31: 10+ | B31: Demonstratives (this/that/these/those) | C31: 5 кл. | D31: 2 | E31: 0 | F31: • this — these (ед. и мн. ч.) • that — those (ед. и мн. ч.)
A32: 10+ | B32: Future Simple (will) | C32: 5 кл. | D32: 2 | E32: 2 | F32: • значение — надежды, страхи, предложения, комментарии • значение — неизбежные события (не зависят от нас) | G32: с видео: 2, вебинар в расписании: 8
A33: 10+ | B33: Possessive case ('s) | C33: 5 кл. | D33: 2 | E33: 2 | F33: • значение — отношения между людьми • магазины, учреждения, чей-то дом (at the baker's) | G33: вебинар в расписании: 5
A34: 10+ | B34: Present Perfect | C34: 5 кл. | D34: 2 | E34: 2 | F34: • значение — неуказанное время в прошлом • значение — акцент на количестве (seven times this week) | G34: с видео: 8, вебинар в расписании: 3
A35: 10+ | B35: Question tags | C35: 5 кл. | D35: 2 | E35: 2 | F35: • have (владеть) → haven't I? vs have в идиоме → don't I? • This/That is → isn't it? | G35: с видео: 3, вебинар в расписании: 5
A36: 10+ | B36: a few/a little | C36: 5 кл. | D36: 2 | E36: 2 | F36: • very few / very little • a little + прилагательное (a little cold) | G36: с видео: 4
A37: 10+ | B37: Object pronouns | C37: 5 кл. | D37: 1 | E37: 1 | F37: • личные vs объектные vs притяжательные — сопоставление | G37: с видео: 2
A38: 10+ | B38: much/many/a lot of | C38: 5 кл. | D38: 1 | E38: 0 | F38: • краткие ответы и a lot / lots без существительного | G38: с видео: 4
A39: 10+ | B39: need/needn't | C39: 6 кл. | D39: 4 | E39: 4 | F39: • needn't / don't need to — нет необходимости (наст./буд.) • needn't have V3 — не было необходимости, но сделали • needn't have vs didn't have to • need (= must) как эквивалент модального
A40: 10+ | B40: Ordinal numbers | C40: 6 кл. | D40: 3 | E40: 0 | F40: • first, second, third и составные (21st, 22nd) • образование с -th и орфография (fifth, ninth, twelfth, twentieth) • с артиклем the и даты
A41: 10+ | B41: have to | C41: 6 кл. | D41: 3 | E41: 3 | F41: • had to — прошедшее время • didn't have to — не было необходимости в прошлом • have got to (= have to) | G41: с видео: 2
A42: 10+ | B42: Stative verbs | C42: 6 кл. | D42: 2 | E42: 2 | F42: • look, feel, hurt, ache — Simple = Continuous • enjoy в Continuous — конкретное удовольствие | G42: с видео: 3
A43: 10+ | B43: Reflexive pronouns | C43: 7 кл. | D43: 5 | E43: 5 | F43: • эмфатическое — «сам» (She will cut the cake herself) • глаголы без возвратного местоимения (wash, dress, meet) • после be, feel, look, seem • после предлогов (но не предлогов места) • устойчивые выражения (Enjoy yourself!, Help yourself, Make yourself at home) | G43: с видео: 3
A44: 10+ | B44: Relative pronouns / Relative clauses | C44: 7 кл. | D44: 5 | E44: 5 | F44: • defining vs non-defining (запятые, без that) • which, относящееся ко всему предложению • of which / whose для предметов • some of / most of + whom/which/whose • that не после запятой и не после предлога | G44: вебинар в расписании: 4
A45: 10+ | B45: Adjectives (general) | C45: 7 кл. | D45: 3 | E45: 3 | F45: • не изменяются по числам • место — перед существительным, после be / look, smell, sound, feel, taste • мнение vs объективные характеристики
A46: 10+ | B46: Comparative structures | C46: 7 кл. | D46: 3 | E46: 3 | F46: • twice / three times / half as … as • the same … as • look/sound/smell/taste + like | G46: с видео: 6
A47: 10+ | B47: Conditionals (Type 1) | C47: 7 кл. | D47: 3 | E47: 3 | F47: • главная часть с Imperative / can, must, may • запятая, если if-часть впереди • unless = if not | G47: с видео: 2
A48: 10+ | B48: Present Perfect Continuous | C48: 7 кл. | D48: 3 | E48: 3 | F48: • значение — раздражение/критика • значение — повторяющиеся действия до настоящего • live/work/teach/feel — без разницы с Present Perfect | G48: с видео: 3
A49: 10+ | B49: used to | C49: 7 кл. | D49: 3 | E49: 3 | F49: • однократное действие — только Past Simple • used to vs be/get used to + -ing • used to и would (used to = would) | G49: с видео: 2
A50: 10+ | B50: Irregular verbs (list) | C50: 7 кл. | D50: 2 | E50: 2 | F50: • таблица Infinitive – Past – Past Participle • двойные и особые формы (burnt/burned, got/gotten, can – could)
A51: 10+ | B51: Past Simple vs Past Continuous | C51: 7 кл. | D51: 2 | E51: 2 | F51: • указанное время — завершённое vs в процессе • последовательные vs одновременные действия | G51: вебинар в расписании: 1
A52: 10+ | B52: Time clauses | C52: 7 кл. | D52: 2 | E52: 2 | F52: • то же после if, unless, in case, supposing • when/if как вопросительное слово или после I don't know/wonder — с will | G52: вебинар в расписании: 2
A53: 10+ | B53: Adjectives (order) | C53: 7 кл. | D53: 1 | E53: 1 | F53: • узор (pattern) в порядке прилагательных | G53: с видео: 2
A54: 10+ | B54: Conditionals (Type 0) | C54: 7 кл. | D54: 1 | E54: 1 | F54: • when вместо if | G54: с видео: 2
A55: 10+ | B55: Partitives (a bottle of…) | C55: 7 кл. | D55: 1 | E55: 1 | F55: • мн. ч. — two bottles of, two loaves of | G55: с видео: 1
A56: 10+ | B56: Past Continuous | C56: 7 кл. | D56: 1 | E56: 1 | F56: • опущение второго was/were при одном подлежащем | G56: с видео: 5
A57: 10+ | B57: Present Perfect vs Past Simple | C57: 7 кл. | D57: 1 | E57: 1 | F57: • закончилось в прошлом vs длится до сих пор | G57: с видео: 1
A58: 10+ | B58: Present Perfect vs Present Perfect Continuous | C58: 7 кл. | D58: 1 | E58: 1 | F58: • эмоциональная окраска Continuous (раздражение) | G58: с видео: 3
A59: 10+ | B59: should/shouldn't | C59: 7 кл. | D59: 1 | E59: 1 | F59: • значение — вероятность ~90% (о будущем) | G59: с видео: 3, вебинар в расписании: 6
A60: 10+ | B60: Passive Voice | C60: 8 кл. | D60: 19 | E60: 19 | F60: • форма be + V3 — Present Simple и Past Simple • Continuous (is/was being + V3) • Present/Past Perfect (has/had been + V3) • Future Simple (will be + V3) • Future Perfect (will have been + V3) • инфинитив и модальные (has to be / can be + V3) • преобразование active → passive • значение — исполнитель неизвестен/неважен/очевиден • значение — действие важнее исполнителя (новости, инструкции, реклама) • значение — уход от ответственности • значение — акцент на исполнителе • значение — формальность, вежливость • by + исполнитель vs with + инструмент/материал • когда агент опускается (they, people, someone…) • глаголы без пассива (непереходные; have, fit, suit, resemble…) • get вместо be • глаголы с двумя дополнениями (give, offer, send…) • by в вопросах с who/whom/which • make/hear/see/help + to-inf в пассиве; see/hear/watch + -ing
A61: 10+ | B61: Phrasal verbs | C61: 8 кл. | D61: 16 | E61: 16 | F61: • bring • call • give • go • put • break • carry • come • keep • make • run • turn • look • pick • do • talk | G61: с видео: 4
A62: 10+ | B62: Infinitive / -ing form | C62: 8 кл. | D62: 15 | E62: 15 | F62: • в роли подлежащего • после spend/waste/lose + время/деньги • -ing vs bare infinitive после see, hear, watch, feel — незавершённое vs завершённое • be/get used to + -ing vs used to + V • после would like/prefer/love — конкретное предпочтение • после too/enough • после be the first/next/last • устойчивые выражения (to tell you the truth, to be honest, to sum up…) • вопросительное слово + to-inf (when to go) • после существительных; so + adj + as to; only + to-inf; for + sb + to-inf • второй инфинитив после and/or без to • dare — с to и без • после модальных, had better, would rather • let/make/see/hear/feel + object + V; в пассиве + to (was made to) • help + (to) V | G62: с видео: 7
A63: 10+ | B63: Infinitive / -ing form (difference in meaning) | C63: 8 кл. | D63: 12 | E63: 12 | F63: • forget/remember • stop • try • regret • mean • go on • hate • want (My car wants cleaning) • be sorry to / for -ing; be afraid to / of -ing • begin, start, continue, intend • advise, allow, encourage, permit, require + object + to-inf / + -ing; в пассиве только to-inf • need/require/want + -ing / to be done (пассивное значение)
A64: 10+ | B64: Reported Speech | C64: 8 кл. | D64: 9 | E64: 9 | F64: • прямая vs косвенная речь, that можно опустить • say vs tell (say to sb, tell sb) • say + to-inf; speak/talk about (не say about) • устойчивые сочетания с say/tell/ask • смена местоимений • без сдвига времён — вводящий глагол в настоящем (up-to-date reporting) • без сдвига времён — общие истины, условные 2/3 типа, wish, сразу после сказанного • сдвиг времён (Present → Past, Past → Past Perfect, will → would) • слова времени и места (now → then, yesterday → the day before…)
A65: 10+ | B65: Modal verbs (functions) | C65: 8 кл. | D65: 8 | E65: 8 | F65: • вопрос и отрицание (инверсия, not) • + простой инфинитив (наст./буд.) vs + перфектный инфинитив (прошлое) • формы инфинитива — simple / continuous / perfect / perfect continuous • значение — критика (could / should / ought to) • значение — вероятность (will 100% vs should/ought to 90%) • эквиваленты модальных (need, had better, have (got) to, be able to, used to) • значение — предложения (offers/suggestions) • обзор значений модальных (систематизация) | G65: с видео: 2
A66: 10+ | B66: Reported Speech: modal verbs | C66: 8 кл. | D66: 7 | E66: 7 | F66: • modal verbs: will/shall → would • modal verbs: can → could / would be able to • modal verbs: may → might/could • modal verbs: shall → should / would / offered • modal verbs: must → had to (обязанность) / must (вывод) • modal verbs: needn't → didn't need to / didn't have to / wouldn't have to • modal verbs: не меняются (would, could, used to, mustn't, should, might, ought to, had better)
A67: 10+ | B67: Modal verbs (deduction) | C67: 8 кл. | D67: 6 | E67: 6 | F67: • must — уверенность (о настоящем) • may/might/could — вероятность (о настоящем) • can't/couldn't — невозможность (о настоящем) • выводы о прошлом — must/may/might/could/can't + have V3 • вероятность — will (100%) vs should/ought to (90%) • критика — could/should/ought to (+ have V3)
A68: 10+ | B68: Causative (have something done) | C68: 8 кл. | D68: 5 | E68: 5 | F68: • have sth done в разных временах (Continuous, Perfect, Future) • инфинитив, -ing и модальные (to have / having sth done) • отрицания и вопросы с do/does/did • get sth done вместо have • значение — неприятное происшествие (had his car stolen) | G68: с видео: 2
A69: 10+ | B69: Reported questions | C69: 8 кл. | D69: 5 | E69: 5 | F69: • вводящие глаголы ask, inquire, wonder, want to know • специальные вопросы — то же вопросительное слово • общие вопросы — if/whether • прямой порядок слов, без «?», без please/well/oh • сдвиг времён, местоимений и слов времени
A70: 10+ | B70: Reported commands/requests | C70: 8 кл. | D70: 4 | E70: 4 | F70: • приказы — order/tell + sb + (not) to-inf • ask/beg + sb + (not) to-inf • suggest + -ing / that sb (should) … • advise + sb + (not) to-inf
A71: 10+ | B71: can/could (ability past) | C71: 8 кл. | D71: 4 | E71: 4 | F71: • could — общая способность в прошлом • was/were able to — способность в конкретной ситуации • couldn't — неспособность в прошлом • be able to в других временах (will be able to)
A72: 10+ | B72: may/might | C72: 8 кл. | D72: 4 | E72: 4 | F72: • can — общая (теоретическая) возможность • could/may/might — возможность в конкретной ситуации • возможность в вопросах — can/could/might, но не may • could/might/would + have V3 — было возможно, но не случилось
A73: 10+ | B73: Conditionals (Type 2) | C73: 8 кл. | D73: 3 | E73: 3 | F73: • If + Past Continuous • were/was для I, he, she, it • If I were you — совет | G73: вебинар в расписании: 2
A74: 10+ | B74: be/get used to | C74: 8 кл. | D74: 3 | E74: 3 | F74: • be used to + -ing — привык • get used to + -ing — привыкаю • be/get used to vs used to + V (to — предлог vs частица)
A75: 10+ | B75: Past Perfect | C75: 8 кл. | D75: 2 | E75: 2 | F75: • значение — завершённое действие с результатом в прошлом • с before/after без разницы | G75: с видео: 2
A76: 10+ | B76: Quantifiers | C76: 8 кл. | D76: 2 | E76: 2 | F76: • a couple of, several + исчисляемые мн. ч. • a great deal of, plenty of | G76: с видео: 5
A77: 10+ | B77: have gone to / have been to / have been in | C77: 8 кл. | D77: 2 | E77: 2 | F77: • уехал и не вернулся vs побывал • находится там (в течение периода)
A78: 10+ | B78: too / enough | C78: 8 кл. | D78: 2 | E78: 2 | F78: • enough / not enough + существительное • too … / … enough + to-infinitive | G78: с видео: 2
A79: 10+ | B79: Conditionals (Type 3) | C79: 8 кл. | D79: 1 | E79: 1 | F79: • If + Past Perfect Continuous | G79: вебинар в расписании: 3
A80: 10+ | B80: Dependent prepositions | C80: 8 кл. | D80: 1 | E80: 1 | F80: • Dependent prepositions
A81: 10+ | B81: Past Perfect Continuous | C81: 8 кл. | D81: 1 | E81: 1 | F81: • значение — длительное действие с видимым результатом в прошлом | G81: с видео: 2
A82: 10+ | B82: Words often confused | C82: 8 кл. | D82: 1 | E82: 1 | F82: • Words often confused
A83: 10+ | B83: Clauses of purpose | C83: 9 кл. | D83: 9 | E83: 9 | F83: • to / in order to / so as to + infinitive • so that + can/will, could/would • with the view to / with the aim of + -ing • for + noun/-ing (назначение предмета) • in case + Present / Past • отрицательная цель — so as not / in order not to • отрицательная цель — so that + can't/won't, couldn't/wouldn't • for fear / lest; for fear of • prevent … (from) + -ing / avoid + -ing
A84: 10+ | B84: Inversion | C84: 9 кл. | D84: 8 | E84: 8 | F84: • условные без if — Should/Were/Had + подлежащее • эмфатическая — форма (вспомогательный / do, does, did + подлежащее) • после отрицательных наречий в начале (Never, Rarely, Seldom, Little, Hardly… when, No sooner… than, Not only… but also) • после Only after/by/when/then, Not till/until, Not since — в главном предложении • после So/Such в начале (результат) • согласие после as, so, neither/nor • смысловой глагол после Here/There (There goes the bus — НО There it goes) • в прямой речи после цитаты (said Bill — НО he said)
A85: 10+ | B85: Reporting verbs | C85: 9 кл. | D85: 6 | E85: 6 | F85: • + to-inf (agree, claim, offer, promise, refuse, threaten…) • + sb + to-inf (advise, allow, encourage, order, remind, warn…) • + (предлог +) -ing (accuse sb of, apologise for, deny, insist on, suggest…) • + that-clause (agree, claim, explain, inform sb, promise…) • explain/wonder + вопросительное слово (+ to-inf / clause) • пересказ диалогов — связки, восклицания, краткие ответы, question tags
A86: 10+ | B86: Conditional linkers (unless, provided…) | C86: 9 кл. | D86: 5 | E86: 5 | F86: • unless, provided/providing (that), as long as, on condition (that) • but for, otherwise, or else • what if, supposing, even if • only if (+ инверсия в главном предложении) • will/would/should в if-части (просьба, раздражение, сомнение)
A87: 10+ | B87: Indefinite pronouns (some-/any-/no-/every-) | C87: 9 кл. | D87: 5 | E87: 5 | F87: • some/any/no + неисчисляемые и мн. ч. • some- в вопросах — предложения и просьбы • any в утверждении = «любой, неважно кто/что» • every + ед. ч.; everybody, everything, everywhere • глагол после производных — в ед. ч. | G87: с видео: 6
A88: 10+ | B88: Wishes (I wish / If only) | C88: 9 кл. | D88: 5 | E88: 5 | F88: • I wish / If only + Past Simple/Continuous — желание изменить настоящее • I wish / If only + Past Perfect — сожаление о прошлом • I wish / If only + would + V — раздражение, просьба изменить поведение • were вместо was • If only vs I wish — эмоциональность
A89: 10+ | B89: Clauses of result | C89: 9 кл. | D89: 3 | E89: 3 | F89: • such … that • so … that • as a result / as a consequence / consequently / therefore / so
A90: 10+ | B90: Expressing preference (prefer / would rather) | C90: 9 кл. | D90: 3 | E90: 3 | F90: • prefer + to-inf rather than + bare inf • I'd prefer + to-inf / noun (rather than) — конкретное предпочтение • I'd rather + bare inf (than + bare inf) | G90: с видео: 1
A91: 10+ | B91: so / such | C91: 9 кл. | D91: 3 | E91: 3 | F91: • so + прил./нареч.; so + many/much/few/little + сущ. • such (a/an) + (прил.) + сущ.; such a lot of • so + прил. + a(n) + сущ.
A92: 10+ | B92: Determiners (every/each) | C92: 9 кл. | D92: 2 | E92: 2 | F92: • every vs each — о двух vs о трёх и более • each (one) of / every one of | G92: с видео: 2
A93: 10+ | B93: Future Continuous | C93: 9 кл. | D93: 2 | E93: 2 | F93: • значение — по распорядку/договорённости • значение — вежливый вопрос о планах | G93: с видео: 2
A94: 10+ | B94: would (past habits) | C94: 9 кл. | D94: 2 | E94: 2 | F94: • значение — повторяющиеся действия в прошлом (would + V) • прошлые состояния — только used to
A95: 10+ | B95: Exclamations | C95: 9 кл. | D95: 1 | E95: 1 | F95: • отрицательный вопрос (Isn't it great…!) | G95: вебинар в расписании: 3
A96: 10+ | B96: Like / As | C96: 10 кл. | D96: 3 | E96: 3 | F96: • like — сходство; после feel, look, smell, taste, sound • as — роль, профессия; после regard, describe, be known; as usual, such as, the same as • like vs as — сходство vs реальная роль
A97: 10+ | B97: Semi-modals | C97: 11 кл. | D97: 4 | E97: 4 | F97: • need (= must), have (got) to (= must) • had better (= should) • be able to (= can) • used to (= would)
A98: 10+ | B98: Clauses of reason | C98: 11 кл. | D98: 3 | E98: 3 | F98: • as / because / for / on the grounds that • the reason for / the reason (why) • because of / due to (+ the fact that)
A99: 10+ | B99: must/have to (obligation) | C99: 11 кл. | D99: 3 | E99: 3 | F99: • must vs have to — субъективная vs объективная необходимость • had to — прошедшее для must и have to • should/ought to — долг, слабая обязанность
A100: 10+ | B100: So / Neither / Nor (agreement) | C100: 11 кл. | D100: 2 | E100: 2 | F100: • So + aux + подлежащее — к утверждению • Neither/Nor + aux + подлежащее — к отрицанию
...

Sheet Итоги
A1: Группа | B1: Классы | C1: Уроков сделать | D1: Есть видео (зелёные) | E1: Вебинар в расписании (жёлтые) | F1: Только материалы (оранжевые) | G1: Ничего нет (красные) | H1: Готовы | I1: Опубликованы | J1: Мест в папках (урок × класс × модуль)
A2: 7–9 | B2: 3, 4 | C2: =COUNTIF('Уроки'!B:B,"7–9") | D2: =COUNTIFS('Уроки'!B:B,"7–9",'Уроки'!H:H,"видео") | E2: =COUNTIFS('Уроки'!B:B,"7–9",'Уроки'!H:H,"вебинар") | F2: =COUNTIFS('Уроки'!B:B,"7–9",'Уроки'!H:H,"материалы") | G2: =COUNTIFS('Уроки'!B:B,"7–9",'Уроки'!H:H,"нет") | H2: =COUNTIFS('Уроки'!B:B,"7–9",'Уроки'!J:J,"готов*") | I2: =COUNTIFS('Уроки'!B:B,"7–9",'Уроки'!J:J,"опубликован") | J2: =COUNTIF('Папки уроков'!I:I,"7–9")
A3: 10+ | B3: 5, 6, 7, 8, 9, 10, 11 | C3: =COUNTIF('Уроки'!B:B,"10+") | D3: =COUNTIFS('Уроки'!B:B,"10+",'Уроки'!H:H,"видео") | E3: =COUNTIFS('Уроки'!B:B,"10+",'Уроки'!H:H,"вебинар") | F3: =COUNTIFS('Уроки'!B:B,"10+",'Уроки'!H:H,"материалы") | G3: =COUNTIFS('Уроки'!B:B,"10+",'Уроки'!H:H,"нет") | H3: =COUNTIFS('Уроки'!B:B,"10+",'Уроки'!J:J,"готов*") | I3: =COUNTIFS('Уроки'!B:B,"10+",'Уроки'!J:J,"опубликован") | J3: =COUNTIF('Папки уроков'!I:I,"10+")
